Workbook

Sheet DIARIO 2023
A1: OR | B1: FECHA | C1: Nº Socio | D1: NOMBRE | E1: COG. | F1: CONCEPTO | G1: Amplia concepto | H1: Importe | I1: Matri | J1: Transf.
A2: 1 | B2: 44935 | C2: 2003 | D2: CARMEN SORIANO PARRA | E2: 1 | F2: =IFERROR(LOOKUP(E2,CODIGOS!A:A,CODIGOS!B:B)," ") -> CUOTA SOCIO | H2: 20 | I2: SI
A3: 2 | B3: 44935 | C3: 1930 | D3: MANUEL CORRALES CARRETERO | E3: 1 | F3: =IFERROR(LOOKUP(E3,CODIGOS!A:A,CODIGOS!B:B)," ") -> CUOTA SOCIO | H3: 20 | I3: SI
A4: 3 | B4: 44935 | C4: 2004 | D4: FRANCIS MANGAS MACIAS | E4: 1 | F4: =IFERROR(LOOKUP(E4,CODIGOS!A:A,CODIGOS!B:B)," ") -> CUOTA SOCIO | H4: 20 | I4: SI
A5: 4 | B5: 44935 | C5: 2324 | D5: GRACIAS FIESTA MORILLA | E5: 1 | F5: =IFERROR(LOOKUP(E5,CODIGOS!A:A,CODIGOS!B:B)," ") -> CUOTA SOCIO | H5: 20 | I5: SI
A6: 5 | B6: 44935 | C6: 2392 | D6: ANA SANCHEZ GONZALEZ | E6: 1 | F6: =IFERROR(LOOKUP(E6,CODIGOS!A:A,CODIGOS!B:B)," ") -> CUOTA SOCIO | H6: 20 | I6: SI
A7: 6 | B7: 44935 | C7: 2570 | D7: JOSE ENRIQUE GARCIA FERNANDEZ | E7: 1 | F7: =IFERROR(LOOKUP(E7,CODIGOS!A:A,CODIGOS!B:B)," ") -> CUOTA SOCIO | H7: 20 | I7: SI
A8: 7 | B8: 44935 | C8: 2571 | D8: ENCARNACION CHINCHILLA FERNANDEZ | E8: 1 | F8: =IFERROR(LOOKUP(E8,CODIGOS!A:A,CODIGOS!B:B)," ") -> CUOTA SOCIO | H8: 20 | I8: SI
A9: 8 | B9: 44935 | C9: 1680 | D9: LOLI CONTRERAS GONZALEZ | E9: 1 | F9: =IFERROR(LOOKUP(E9,CODIGOS!A:A,CODIGOS!B:B)," ") -> CUOTA SOCIO | H9: 20 | I9: SI
A10: 9 | B10: 44935 | C10: 2105 | D10: ISABEL NAVARRO DE OÑA | E10: 1 | F10: =IFERROR(LOOKUP(E10,CODIGOS!A:A,CODIGOS!B:B)," ") -> CUOTA SOCIO | H10: 20 | I10: NO
A11: 10 | B11: 44935 | C11: 575 | D11: TERESA BAUTISTA MENDEZ | E11: 1 | F11: =IFERROR(LOOKUP(E11,CODIGOS!A:A,CODIGOS!B:B)," ") -> CUOTA SOCIO | H11: 20 | I11: NO
A12: 11 | B12: 44935 | C12: 410 | D12: LUCIA LOPEZ BIEZMA | E12: 1 | F12: =IFERROR(LOOKUP(E12,CODIGOS!A:A,CODIGOS!B:B)," ") -> CUOTA SOCIO | H12: 20 | I12: NO
A13: 12 | B13: 44935 | C13: A/410 | D13: EMILIA HITA ROMERO | E13: 1 | F13: =IFERROR(LOOKUP(E13,CODIGOS!A:A,CODIGOS!B:B)," ") -> CUOTA SOCIO | H13: 30 | I13: NO
A14: 13 | B14: 44935 | C14: 2555 | D14: ANTONIO LARA ARCOS | E14: 1 | F14: =IFERROR(LOOKUP(E14,CODIGOS!A:A,CODIGOS!B:B)," ") -> CUOTA SOCIO | H14: 20 | I14: SI
A15: 14 | B15: 44935 | C15: 1982 | D15: Mª LUISA GARZON VALDEARENAS | E15: 1 | F15: =IFERROR(LOOKUP(E15,CODIGOS!A:A,CODIGOS!B:B)," ") -> CUOTA SOCIO | H15: 20 | I15: SI
A16: 15 | B16: 44935 | C16: A/2555 | D16: Mª AGEDA MARTIN RUEDA | E16: 1 | F16: =IFERROR(LOOKUP(E16,CODIGOS!A:A,CODIGOS!B:B)," ") -> CUOTA SOCIO | H16: 30 | I16: NO
A17: 16 | B17: 44935 | C17: 2489 | D17: PILAR TORRES PEREA | E17: 1 | F17: =IFERROR(LOOKUP(E17,CODIGOS!A:A,CODIGOS!B:B)," ") -> CUOTA SOCIO | H17: 20 | I17: SI
A18: 17 | B18: 44936 | C18: 2131 | D18: ANTONIO SANCHEZ GARCIA | E18: 1 | F18: =IFERROR(LOOKUP(E18,CODIGOS!A:A,CODIGOS!B:B)," ") -> CUOTA SOCIO | H18: 20 | I18: SI
A19: 18 | B19: 44936 | C19: A/2131 | D19: Mª ANGUSTIAS MOLINA QUESADA | E19: 1 | F19: =IFERROR(LOOKUP(E19,CODIGOS!A:A,CODIGOS!B:B)," ") -> CUOTA SOCIO | H19: 30 | I19: NO
A20: 19 | B20: 44936 | C20: 2559 | D20: Mª JOSE DIAZ CARRILLO | E20: 1 | F20: =IFERROR(LOOKUP(E20,CODIGOS!A:A,CODIGOS!B:B)," ") -> CUOTA SOCIO | H20: 20 | I20: SI
A21: 20 | B21: 44936 | C21: 2588 | D21: INMACULADA DIAZ FLORES | E21: 2 | F21: =IFERROR(LOOKUP(E21,CODIGOS!A:A,CODIGOS!B:B)," ") -> CUOTA NUEVO SOCIO | H21: 5 | I21: SI
A22: 21 | B22: 44936 | C22: 2314 | D22: Eloy de Haro Muñoz | E22: 2 | F22: =IFERROR(LOOKUP(E22,CODIGOS!A:A,CODIGOS!B:B)," ") -> CUOTA NUEVO SOCIO | H22: 5
A23: 22 | B23: 44936 | C23: 2315 | D23: Mª Consolación Romero González | E23: 2 | F23: =IFERROR(LOOKUP(E23,CODIGOS!A:A,CODIGOS!B:B)," ") -> CUOTA NUEVO SOCIO | H23: 5
A24: 23 | B24: 44936 | C24: 2471 | D24: Mª Jesús Sánchez Pérez | E24: 1 | F24: =IFERROR(LOOKUP(E24,CODIGOS!A:A,CODIGOS!B:B)," ") -> CUOTA SOCIO | H24: 20
A25: 24 | B25: 44937 | C25: 2492 | D25: INMACULADA CABALLERO BUENO | E25: 2 | F25: =IFERROR(LOOKUP(E25,CODIGOS!A:A,CODIGOS!B:B)," ") -> CUOTA NUEVO SOCIO | H25: 5
A26: 25 | B26: 44937 | C26: 2414 | D26: FRANCISCA GARCIA GOMEZ | E26: 1 | F26: =IFERROR(LOOKUP(E26,CODIGOS!A:A,CODIGOS!B:B)," ") -> CUOTA SOCIO | H26: 20 | I26: SI
A27: 26 | B27: 44937 | C27: 2456 | D27: SEBASTIAN TELLEZ SANCHEZ | E27: 1 | F27: =IFERROR(LOOKUP(E27,CODIGOS!A:A,CODIGOS!B:B)," ") -> CUOTA SOCIO | H27: 20 | I27: NO
A28: 27 | B28: 44937 | C28: 2557 | D28: Mª JOSE HERNANDEZ CASADO | E28: 55 | F28: =IFERROR(LOOKUP(E28,CODIGOS!A:A,CODIGOS!B:B)," ") -> 0 | H28: 25 | I28: SI
A29: 28 | B29: 44937 | C29: 2706 | D29: ANTONIO CAMERO CIFUENTES | E29: 2 | F29: =IFERROR(LOOKUP(E29,CODIGOS!A:A,CODIGOS!B:B)," ") -> CUOTA NUEVO SOCIO | H29: 5
A30: 29 | B30: 44942 | C30: 1823 | D30: INMA CAÑAVATE | E30: 1 | F30: =IFERROR(LOOKUP(E30,CODIGOS!A:A,CODIGOS!B:B)," ") -> CUOTA SOCIO | H30: 20 | I30: SI
A31: 30 | B31: 44942 | C31: 1433 | D31: JOSE RODRIGUEZ SANCHEZ | E31: 2 | F31: =IFERROR(LOOKUP(E31,CODIGOS!A:A,CODIGOS!B:B)," ") -> CUOTA NUEVO SOCIO | H31: 15 | I31: 3
A32: 31 | B32: 44943 | C32: 2679 | D32: ENCARNITA MORENO ZURITA | E32: 3 | F32: =IFERROR(LOOKUP(E32,CODIGOS!A:A,CODIGOS!B:B)," ") -> 0 | H32: 5
A33: 32 | B33: 44943 | C33: A/1920 | D33: Josefa Sancho Lledó | E33: 1 | F33: =IFERROR(LOOKUP(E33,CODIGOS!A:A,CODIGOS!B:B)," ") -> CUOTA SOCIO | H33: 20
A34: 33 | B34: 44944 | C34: 1920 | D34: PEPE HERAS | E34: 4 | F34: =IFERROR(LOOKUP(E34,CODIGOS!A:A,CODIGOS!B:B)," ") -> DEVOLUCION | H34: 15 | I34: SI
A35: 34 | B35: 44944 | C35: 2563 | D35: VICTORIANO MARTIN | E35: 4 | F35: =IFERROR(LOOKUP(E35,CODIGOS!A:A,CODIGOS!B:B)," ") -> DEVOLUCION | H35: 15 | I35: SI
A36: 35 | B36: 44944 | C36: A/1920 | D36: PEPA SÁNCHO | E36: 4 | F36: =IFERROR(LOOKUP(E36,CODIGOS!A:A,CODIGOS!B:B)," ") -> DEVOLUCION | H36: 15 | I36: NO
A37: 36 | B37: 44944 | C37: 269 | D37: JUAN FRANCISCO ACEÑA CABALLERO | E37: 4 | F37: =IFERROR(LOOKUP(E37,CODIGOS!A:A,CODIGOS!B:B)," ") -> DEVOLUCION | H37: 15 | I37: SI
A38: 37 | B38: 44944 | C38: A/269 | D38: Mª ÁNGELES PALOMINO PALOMINO | E38: 5 | F38: =IFERROR(LOOKUP(E38,CODIGOS!A:A,CODIGOS!B:B)," ") -> 0 | H38: 20 | I38: NO
A39: 38 | B39: 44944 | C39: 2632 | D39: ANTONIO BAENA CORTÉS | E39: 5 | F39: =IFERROR(LOOKUP(E39,CODIGOS!A:A,CODIGOS!B:B)," ") -> 0 | H39: 15 | I39: SI
A40: 39 | B40: 44944 | C40: 2553 | D40: JOSÉ J. PÉREZ BLANCO | E40: 5 | F40: =IFERROR(LOOKUP(E40,CODIGOS!A:A,CODIGOS!B:B)," ") -> 0 | H40: 15 | I40: SI
A41: 40 | B41: 44944 | C41: 2720 | D41: JUAN ÁLVAREZ ARIAS | E41: 55 | F41: =IFERROR(LOOKUP(E41,CODIGOS!A:A,CODIGOS!B:B)," ") -> 0 | H41: 25 | I41: SI
A42: 41 | B42: 44949 | C42: 2108 | D42: MARGARITA BLASCO AZAUSTRE | E42: 4 | F42: =IFERROR(LOOKUP(E42,CODIGOS!A:A,CODIGOS!B:B)," ") -> DEVOLUCION | H42: 15 | I42: SI
A43: 42 | B43: 44949 | C43: 2109 | D43: Mª LUZ BELTRAN CABRERA | E43: 4 | F43: =IFERROR(LOOKUP(E43,CODIGOS!A:A,CODIGOS!B:B)," ") -> DEVOLUCION | H43: 15 | I43: SI
A44: 43 | B44: 44949 | C44: 2610 | D44: Mª ANGUSTIA MIRANDA LOPEZ | E44: 4 | F44: =IFERROR(LOOKUP(E44,CODIGOS!A:A,CODIGOS!B:B)," ") -> DEVOLUCION | H44: 15 | I44: SI
A45: 44 | B45: 44949 | C45: 2527 | D45: JOSE ANT RAMIREZ GARCIA | E45: 4 | F45: =IFERROR(LOOKUP(E45,CODIGOS!A:A,CODIGOS!B:B)," ") -> DEVOLUCION | H45: 15 | I45: SI
A46: 45 | B46: 44949 | C46: 2612 | D46: ANTONIO ISIDRO GALLEGO LORCA | E46: 4 | F46: =IFERROR(LOOKUP(E46,CODIGOS!A:A,CODIGOS!B:B)," ") -> DEVOLUCION | H46: 15 | I46: SI
A47: 46 | B47: 44949 | C47: 1913 | D47: LOURDES ROZUA LARIOS | E47: 4 | F47: =IFERROR(LOOKUP(E47,CODIGOS!A:A,CODIGOS!B:B)," ") -> DEVOLUCION | H47: 15 | I47: SI
A48: 47 | B48: 44949 | C48: 738 | D48: Mª TERESA ROZUA LARIOS | E48: 4 | F48: =IFERROR(LOOKUP(E48,CODIGOS!A:A,CODIGOS!B:B)," ") -> DEVOLUCION | H48: 15 | I48: SI
A49: 48 | B49: 44949 | C49: 2636 | D49: FRANCISCO MARTINEZ HIDALGO | E49: 4 | F49: =IFERROR(LOOKUP(E49,CODIGOS!A:A,CODIGOS!B:B)," ") -> DEVOLUCION | H49: 15 | I49: SI
A50: 49 | B50: 44949 | C50: 2484 | D50: Mª ANGELES ILLESCA PEREZ | E50: 4 | F50: =IFERROR(LOOKUP(E50,CODIGOS!A:A,CODIGOS!B:B)," ") -> DEVOLUCION | H50: 15 | I50: SI
... A56: 55 | B56: 44950 | C56: 2718 | D56: Maria Rosario Martín Bueno | E56: 55 | F56: =IFERROR(LOOKUP(E56,CODIGOS!A:A,CODIGOS!B:B)," ") -> 0 | H56: 25 | I56: Si
A57: 56 | B57: 44951 | C57: A/2588 | D57: JUAN MANUEL CARA GARCIA | E57: 2 | F57: =IFERROR(LOOKUP(E57,CODIGOS!A:A,CODIGOS!B:B)," ") -> CUOTA NUEVO SOCIO | H57: 5 | I57: NO
A58: 57 | B58: 44956 | C58: 2581 | D58: ANA FERNANDEZ BARAZA | E58: 5 | F58: =IFERROR(LOOKUP(E58,CODIGOS!A:A,CODIGOS!B:B)," ") -> 0 | H58: 15 | I58: SI
A59: 58 | B59: 44956 | C59: 2575 | D59: Mª ANGELES FERNANDEZ GARCIA | E59: 5 | F59: =IFERROR(LOOKUP(E59,CODIGOS!A:A,CODIGOS!B:B)," ") -> 0 | H59: 15 | I59: SI
A60: 59 | B60: 44956 | C60: 1897 | D60: RAFAEL BAENA CORTES | E60: 5 | F60: =IFERROR(LOOKUP(E60,CODIGOS!A:A,CODIGOS!B:B)," ") -> 0 | H60: 15 | I60: SI
A61: 60 | B61: 44956 | C61: 1898 | D61: ESPERANZA CARMONA CASAS | E61: 5 | F61: =IFERROR(LOOKUP(E61,CODIGOS!A:A,CODIGOS!B:B)," ") -> 0 | H61: 15 | I61: SI
A62: 61 | B62: 44956 | C62: 2567 | D62: ANA ROMERO FUNES | E62: 5 | F62: =IFERROR(LOOKUP(E62,CODIGOS!A:A,CODIGOS!B:B)," ") -> 0 | H62: 15 | I62: SI
A63: 62 | B63: 44956 | C63: 2568 | D63: FRANCISCO MALAGON VILLEN | E63: 5 | F63: =IFERROR(LOOKUP(E63,CODIGOS!A:A,CODIGOS!B:B)," ") -> 0 | H63: 15 | I63: SI
A64: 63 | B64: 44956 | C64: 2616 | D64: ANTONIO VIGIL LOPEZ | E64: 5 | F64: =IFERROR(LOOKUP(E64,CODIGOS!A:A,CODIGOS!B:B)," ") -> 0 | H64: 15 | I64: SI
A65: 64 | B65: 44956 | C65: A/2616 | D65: Mª LUCIA ARIAS UCLES | E65: 5 | F65: =IFERROR(LOOKUP(E65,CODIGOS!A:A,CODIGOS!B:B)," ") -> 0 | H65: 20 | I65: N0
A66: 65 | B66: 44956 | C66: 2667 | D66: Mª ROSA LOPEZ NAVARRETE | E66: 5 | F66: =IFERROR(LOOKUP(E66,CODIGOS!A:A,CODIGOS!B:B)," ") -> 0 | H66: 15 | I66: NO
A67: 66 | B67: 44956 | C67: A/2667 | D67: FRANCISCA RUIZ ORTEGA | E67: 5 | F67: =IFERROR(LOOKUP(E67,CODIGOS!A:A,CODIGOS!B:B)," ") -> 0 | H67: 20 | I67: NO
A68: 67 | B68: 44956 | C68: 2719 | D68: CASILDA FERNANDEZ SALIDO | E68: 55 | F68: =IFERROR(LOOKUP(E68,CODIGOS!A:A,CODIGOS!B:B)," ") -> 0 | H68: 25 | I68: NO
A69: 68 | B69: 44956 | C69: 2663 | D69: ANTONIO CARRILLO SANCHEZ | E69: 5 | F69: =IFERROR(LOOKUP(E69,CODIGOS!A:A,CODIGOS!B:B)," ") -> 0 | H69: 15 | I69: SI
A70: 69 | B70: 44956 | C70: 2004 | D70: FRANCIS MANGAS MACIAS | E70: 5 | F70: =IFERROR(LOOKUP(E70,CODIGOS!A:A,CODIGOS!B:B)," ") -> 0 | H70: 15 | I70: SI
A71: 70 | B71: 44956 | C71: 2003 | D71: CARMEN SORIANO PARRA | E71: 5 | F71: =IFERROR(LOOKUP(E71,CODIGOS!A:A,CODIGOS!B:B)," ") -> 0 | H71: 15 | I71: SI
A72: 71 | B72: 44957 | C72: 2416 | D72: JUAN JESUS TOMAS SALAZAR | E72: 5 | F72: =IFERROR(LOOKUP(E72,CODIGOS!A:A,CODIGOS!B:B)," ") -> 0 | H72: 15
A73: 72 | B73: 44957 | C73: A/2416 | D73: ANA ROJAS FERNANDEZ | E73: 5 | F73: =IFERROR(LOOKUP(E73,CODIGOS!A:A,CODIGOS!B:B)," ") -> 0 | H73: 20
A74: 73 | B74: 44957 | C74: 2015 | D74: JUAN VALVERDE GARCIA | E74: 55 | F74: =IFERROR(LOOKUP(E74,CODIGOS!A:A,CODIGOS!B:B)," ") -> 0 | H74: 25
A75: 74 | B75: 44957 | C75: 2136 | D75: MARIA ANGUSTIAS SPINOLA GOMEZ | E75: 55 | F75: =IFERROR(LOOKUP(E75,CODIGOS!A:A,CODIGOS!B:B)," ") -> 0 | H75: 25
A76: 75 | B76: 44957 | C76: 2015 | D76: JUAN VALVERDE GARCIA | E76: 5 | F76: =IFERROR(LOOKUP(E76,CODIGOS!A:A,CODIGOS!B:B)," ") -> 0 | H76: 15
A77: 76 | B77: 44957 | C77: 2136 | D77: MARIA ANGUSTIAS SPINOLA GOMEZ | E77: 5 | F77: =IFERROR(LOOKUP(E77,CODIGOS!A:A,CODIGOS!B:B)," ") -> 0 | H77: 15
A78: 77 | B78: 44957 | C78: 2456 | D78: SEBASTIAN TELLEZ SANCHEZ | E78: 5 | F78: =IFERROR(LOOKUP(E78,CODIGOS!A:A,CODIGOS!B:B)," ") -> 0 | H78: 15
A79: 78 | B79: 44957 | C79: 2414 | D79: FRANCISCA GARCIA GOMEZ | E79: 5 | F79: =IFERROR(LOOKUP(E79,CODIGOS!A:A,CODIGOS!B:B)," ") -> 0 | H79: 15
A80: 79 | B80: 44957 | C80: 2679 | D80: NANI MORENO ZURITA | E80: 5 | F80: =IFERROR(LOOKUP(E80,CODIGOS!A:A,CODIGOS!B:B)," ") -> 0 | H80: 15
A81: 80 | B81: 44957 | C81: 2576 | D81: CARMEN RUZ GUZMAN | E81: 4 | F81: =IFERROR(LOOKUP(E81,CODIGOS!A:A,CODIGOS!B:B)," ") -> DEVOLUCION | H81: 15
A82: 81 | B82: 44957 | C82: 1920 | D82: PEPE HERAS | E82: 4 | F82: =IFERROR(LOOKUP(E82,CODIGOS!A:A,CODIGOS!B:B)," ") -> DEVOLUCION | H82: 15 | I82: SI
A83: 82 | B83: 44957 | C83: 2563 | D83: VICTORIANO MARTIN | E83: 4 | F83: =IFERROR(LOOKUP(E83,CODIGOS!A:A,CODIGOS!B:B)," ") -> DEVOLUCION | H83: 15 | I83: SI
A84: 83 | B84: 44957 | C84: A/1920 | D84: PEPA SÁNCHO | E84: 4 | F84: =IFERROR(LOOKUP(E84,CODIGOS!A:A,CODIGOS!B:B)," ") -> DEVOLUCION | H84: 15 | I84: NO
A85: 84 | B85: 44957 | C85: 269 | D85: JUAN FRANCISCO ACEÑA CABALLERO | E85: 5 | F85: =IFERROR(LOOKUP(E85,CODIGOS!A:A,CODIGOS!B:B)," ") -> 0 | H85: 15 | I85: SI
A86: 85 | B86: 44957 | C86: A/269 | D86: Mª ÁNGELES PALOMINO PALOMINO | E86: 5 | F86: =IFERROR(LOOKUP(E86,CODIGOS!A:A,CODIGOS!B:B)," ") -> 0 | H86: 20 | I86: NO
A87: 86 | B87: 44957 | C87: 2632 | D87: ANTONIO BAENA CORTÉS | E87: 5 | F87: =IFERROR(LOOKUP(E87,CODIGOS!A:A,CODIGOS!B:B)," ") -> 0 | H87: 15 | I87: SI
A88: 87 | B88: 44957 | C88: 2553 | D88: JOSÉ J. PÉREZ BLANCO | E88: 5 | F88: =IFERROR(LOOKUP(E88,CODIGOS!A:A,CODIGOS!B:B)," ") -> 0 | H88: 15 | I88: SI
A89: 88 | B89: 44957 | C89: 2720 | D89: JUAN ÁLVAREZ ARIAS | E89: 55 | F89: =IFERROR(LOOKUP(E89,CODIGOS!A:A,CODIGOS!B:B)," ") -> 0 | H89: 25 | I89: SI
A90: 89 | B90: 44963 | C90: 2403 | D90: JENARO MUÑOZ ROPERO | E90: 5 | F90: =IFERROR(LOOKUP(E90,CODIGOS!A:A,CODIGOS!B:B)," ") -> 0 | H90: 15 | I90: SI
A91: 90 | B91: 44963 | C91: 2374 | D91: SAGRARIO LUNA POLO | E91: 5 | F91: =IFERROR(LOOKUP(E91,CODIGOS!A:A,CODIGOS!B:B)," ") -> 0 | H91: 15 | I91: SI
A92: 91 | B92: 44963 | C92: 2581 | D92: ANA FERNANDEZ BARAZA | E92: 6 | F92: =IFERROR(LOOKUP(E92,CODIGOS!A:A,CODIGOS!B:B)," ") -> 0 | H92: 20 | I92: SI
A93: 92 | B93: 44963 | C93: 1913 | D93: LOURDES ROZUA LARIOS | E93: 6 | F93: =IFERROR(LOOKUP(E93,CODIGOS!A:A,CODIGOS!B:B)," ") -> 0 | H93: 20 | I93: SI
A94: 93 | B94: 44963 | C94: 738 | D94: Mª TERESA ROZUA LARIOS | E94: 6 | F94: =IFERROR(LOOKUP(E94,CODIGOS!A:A,CODIGOS!B:B)," ") -> 0 | H94: 20 | I94: SI
A95: 94 | B95: 44963 | C95: 2575 | D95: mº ANGELES GARCIA FERNANDEZ | E95: 6 | F95: =IFERROR(LOOKUP(E95,CODIGOS!A:A,CODIGOS!B:B)," ") -> 0 | H95: 20 | I95: SI
A96: 95 | B96: 44963 | C96: 2571 | D96: ENCARNA CHINCHILLA FERNANDEZ | E96: 6 | F96: =IFERROR(LOOKUP(E96,CODIGOS!A:A,CODIGOS!B:B)," ") -> 0 | H96: 20 | I96: SI
A97: 96 | B97: 44963 | C97: 2612 | D97: ANT ISIDRO GALLEGO LORCA | E97: 6 | F97: =IFERROR(LOOKUP(E97,CODIGOS!A:A,CODIGOS!B:B)," ") -> 0 | H97: 20 | I97: SI
A98: 97 | B98: 44963 | C98: 2324 | D98: GRACIAS FERNANDEZ MORILLA | E98: 6 | F98: =IFERROR(LOOKUP(E98,CODIGOS!A:A,CODIGOS!B:B)," ") -> 0 | H98: 20 | I98: SI
... A104: 103 | B104: 44963 | C104: 2129 | D104: Mª ANGUSTIAS CALVO LOPEZ | E104: 6 | F104: =IFERROR(LOOKUP(E104,CODIGOS!A:A,CODIGOS!B:B)," ") -> 0 | H104: 20 | I104: SI
A105: 104 | B105: 44963 | C105: A/2303 | D105: PILAR TORRES PEREA | E105: 6 | F105: =IFERROR(LOOKUP(E105,CODIGOS!A:A,CODIGOS!B:B)," ") -> 0 | H105: 30 | I105: NO
A106: 105 | B106: 44963 | C106: 1397 | D106: RAFAEL RECHE SILVA | E106: 6 | F106: =IFERROR(LOOKUP(E106,CODIGOS!A:A,CODIGOS!B:B)," ") -> 0 | H106: 40 | I106: SI
A107: 106 | B107: 44963 | C107: A/1397 | D107: MARIBEL ALBARADO GALLEGO | E107: 6 | F107: =IFERROR(LOOKUP(E107,CODIGOS!A:A,CODIGOS!B:B)," ") -> 0
A108: 107 | B108: 44963 | C108: 2721 | D108: Mª ELENA ESPINAR GONZALEZ | E108: 6 | F108: =IFERROR(LOOKUP(E108,CODIGOS!A:A,CODIGOS!B:B)," ") -> 0 | H108: 25 | I108: SI
A109: 108 | B109: 44963 | C109: 1930 | D109: MANUEL CORRALES CARRETERO | E109: 6 | F109: =IFERROR(LOOKUP(E109,CODIGOS!A:A,CODIGOS!B:B)," ") -> 0 | H109: 20 | I109: SI
A110: 109 | B110: 44963 | C110: 2004 | D110: FRANCIS MANGAS MACIAS | E110: 6 | F110: =IFERROR(LOOKUP(E110,CODIGOS!A:A,CODIGOS!B:B)," ") -> 0 | H110: 20 | I110: SI
...

Sheet DIARIO 2026
A1: OR | B1: FECHA | C1: Nº Socio | D1: NOMBRE | E1: COG. | F1: CONCEPTO | H1: Importe | I1: Matriculado | J1: SOCIO | K1: Transf.
A2: 1 | D2: NO ESCRIBIR | F2: =IFERROR(LOOKUP(E2,CODIGOS!A:A,CODIGOS!B:B)," ") | I2: =IFERROR(LOOKUP(C2,SOCIO!A:A,SOCIO!D:D)," ")
A3: =IF(B3<>0,A2+1," ") -> 2 | B3: 46034 | C3: 2823 | D3: CORRAL SOLA, MARÍA | E3: 11 | F3: =IFERROR(LOOKUP(E3,CODIGOS!A:A,CODIGOS!B:B)," ") -> OLLA SAN ANTÓN | H3: =IF(I3="SI",IFERROR(LOOKUP(E3,CODIGOS!A:A,CODIGOS!C:C)," "),IFERROR(LOOKUP(E3,CODIGOS!A:A,CODIGOS!D:D),"")) -> 25 | I3: =IFERROR(LOOKUP(C3,SOCIO!A:A,SOCIO!D:D)," ") -> SI | J3: =IFERROR(LOOKUP(D3,SOCIO!B:B,SOCIO!C:C)," ") -> SI
A4: =IF(B4<>0,A3+1," ") -> 3 | B4: 46034 | C4: 2823 | D4: CORRAL SOLA, MARÍA | E4: 12 | F4: =IFERROR(LOOKUP(E4,CODIGOS!A:A,CODIGOS!B:B)," ") -> EXPOSICIÓN CATEDRAL | H4: =IF(J4="SI",IFERROR(LOOKUP(E4,CODIGOS!A:A,CODIGOS!C:C)," "),IFERROR(LOOKUP(E4,CODIGOS!A:A,CODIGOS!D:D),"")) -> 3 | I4: NO | J4: =IFERROR(LOOKUP(D4,SOCIO!B:B,SOCIO!C:C)," ") -> SI
A5: =IF(B5<>0,A4+1," ") -> 4 | B5: 46034 | C5: A/1920 | D5: SANCHO LLEDÓ, PEPA | E5: 11 | F5: =IFERROR(LOOKUP(E5,CODIGOS!A:A,CODIGOS!B:B)," ") -> OLLA SAN ANTÓN | H5: =IF(J5="SI",IFERROR(LOOKUP(E5,CODIGOS!A:A,CODIGOS!C:C)," "),IFERROR(LOOKUP(E5,CODIGOS!A:A,CODIGOS!D:D),"")) -> 25 | I5: =IFERROR(LOOKUP(C5,SOCIO!A:A,SOCIO!D:D)," ") | J5: =IFERROR(LOOKUP(D5,SOCIO!B:B,SOCIO!C:C)," ") -> SI
A6: =IF(B6<>0,A5+1," ") -> 5 | B6: 46034 | C6: A/2498 | D6: ABAD ORTEGA, MARIA DEL MARº | E6: 11 | F6: =IFERROR(LOOKUP(E6,CODIGOS!A:A,CODIGOS!B:B)," ") -> OLLA SAN ANTÓN | H6: =IF(J6="SI",IFERROR(LOOKUP(E6,CODIGOS!A:A,CODIGOS!C:C)," "),IFERROR(LOOKUP(E6,CODIGOS!A:A,CODIGOS!D:D),"")) -> 30 | I6: =IFERROR(LOOKUP(C6,SOCIO!A:A,SOCIO!D:D)," ") | J6: =IFERROR(LOOKUP(D6,SOCIO!B:B,SOCIO!C:C)," ")
A7: =IF(B7<>0,A6+1," ") -> 6 | B7: 46034 | C7: 1920 | D7: HERAS JIMENEZ, JOSE FRANCISCO | E7: 12 | F7: =IFERROR(LOOKUP(E7,CODIGOS!A:A,CODIGOS!B:B)," ") -> EXPOSICIÓN CATEDRAL | H7: =IF(J7="SI",IFERROR(LOOKUP(E7,CODIGOS!A:A,CODIGOS!C:C)," "),IFERROR(LOOKUP(E7,CODIGOS!A:A,CODIGOS!D:D),"")) -> 3 | I7: =IFERROR(LOOKUP(C7,SOCIO!A:A,SOCIO!D:D)," ") -> SI | J7: =IFERROR(LOOKUP(D7,SOCIO!B:B,SOCIO!C:C)," ") -> SI
A8: =IF(B8<>0,A7+1," ") -> 7 | B8: 46034 | C8: A/1920 | D8: SANCHO LLEDÓ, PEPA | E8: 12 | F8: =IFERROR(LOOKUP(E8,CODIGOS!A:A,CODIGOS!B:B)," ") -> EXPOSICIÓN CATEDRAL | H8: =IF(J8="SI",IFERROR(LOOKUP(E8,CODIGOS!A:A,CODIGOS!C:C)," "),IFERROR(LOOKUP(E8,CODIGOS!A:A,CODIGOS!D:D),"")) -> 3 | I8: =IFERROR(LOOKUP(C8,SOCIO!A:A,SOCIO!D:D)," ") | J8: =IFERROR(LOOKUP(D8,SOCIO!B:B,SOCIO!C:C)," ") -> SI
A9: =IF(B9<>0,A8+1," ") -> 8 | B9: 46034 | C9: 1920 | D9: HERAS JIMENEZ, JOSE FRANCISCO | E9: 10 | F9: =IFERROR(LOOKUP(E9,CODIGOS!A:A,CODIGOS!B:B)," ") -> ÓRGIVA | H9: =IF(J9="SI",IFERROR(LOOKUP(E9,CODIGOS!A:A,CODIGOS!C:C)," "),IFERROR(LOOKUP(E9,CODIGOS!A:A,CODIGOS!D:D),"")) -> 22 | I9: =IFERROR(LOOKUP(C9,SOCIO!A:A,SOCIO!D:D)," ") -> SI | J9: =IFERROR(LOOKUP(D9,SOCIO!B:B,SOCIO!C:C)," ") -> SI
A10: =IF(B10<>0,A9+1," ") -> 9 | B10: 46034 | C10: A/1920 | D10: SANCHO LLEDÓ, PEPA | E10: 10 | F10: =IFERROR(LOOKUP(E10,CODIGOS!A:A,CODIGOS!B:B)," ") -> ÓRGIVA | H10: =IF(J10="SI",IFERROR(LOOKUP(E10,CODIGOS!A:A,CODIGOS!C:C)," "),IFERROR(LOOKUP(E10,CODIGOS!A:A,CODIGOS!D:D),"")) -> 22 | I10: =IFERROR(LOOKUP(C10,SOCIO!A:A,SOCIO!D:D)," ") | J10: =IFERROR(LOOKUP(D10,SOCIO!B:B,SOCIO!C:C)," ") -> SI
A11: =IF(B11<>0,A10+1," ") -> 10 | B11: 46034 | C11: 2673 | D11: VALDEARENAS, MANUEL | E11: 11 | F11: =IFERROR(LOOKUP(E11,CODIGOS!A:A,CODIGOS!B:B)," ") -> OLLA SAN ANTÓN | H11: =IF(J11="SI",IFERROR(LOOKUP(E11,CODIGOS!A:A,CODIGOS!C:C)," "),IFERROR(LOOKUP(E11,CODIGOS!A:A,CODIGOS!D:D),"")) -> 25 | I11: =IFERROR(LOOKUP(C11,SOCIO!A:A,SOCIO!D:D)," ") -> SI | J11: =IFERROR(LOOKUP(D11,SOCIO!B:B,SOCIO!C:C)," ") -> SI
A12: =IF(B12<>0,A11+1," ") -> 11 | B12: 46034 | C12: 2900 | D12: MURILLO, HELMER | E12: 11 | F12: =IFERROR(LOOKUP(E12,CODIGOS!A:A,CODIGOS!B:B)," ") -> OLLA SAN ANTÓN | H12: =IF(J12="SI",IFERROR(LOOKUP(E12,CODIGOS!A:A,CODIGOS!C:C)," "),IFERROR(LOOKUP(E12,CODIGOS!A:A,CODIGOS!D:D),"")) -> 25 | I12: =IFERROR(LOOKUP(C12,SOCIO!A:A,SOCIO!D:D)," ") -> SI | J12: =IFERROR(LOOKUP(D12,SOCIO!B:B,SOCIO!C:C)," ") -> SI
A13: =IF(B13<>0,A12+1," ") -> 12 | B13: 46034 | C13: A/2900 | D13: MURILLO, FLOR | E13: 11 | F13: =IFERROR(LOOKUP(E13,CODIGOS!A:A,CODIGOS!B:B)," ") -> OLLA SAN ANTÓN | H13: 30 | I13: =IFERROR(LOOKUP(C13,SOCIO!A:A,SOCIO!D:D)," ") | J13: =IFERROR(LOOKUP(D13,SOCIO!B:B,SOCIO!C:C)," ") -> SI
A14: =IF(B14<>0,A13+1," ") -> 13 | B14: 46034 | C14: 2134 | D14: ROLDAN, MARIA | E14: 11 | F14: =IFERROR(LOOKUP(E14,CODIGOS!A:A,CODIGOS!B:B)," ") -> OLLA SAN ANTÓN | H14: =IF(J14="SI",IFERROR(LOOKUP(E14,CODIGOS!A:A,CODIGOS!C:C)," "),IFERROR(LOOKUP(E14,CODIGOS!A:A,CODIGOS!D:D),"")) -> 25 | I14: =IFERROR(LOOKUP(C14,SOCIO!A:A,SOCIO!D:D)," ") -> NO | J14: =IFERROR(LOOKUP(D14,SOCIO!B:B,SOCIO!C:C)," ") -> SI
A15: =IF(B15<>0,A14+1," ") -> 14 | B15: 46034 | C15: 2961 | D15: ESPINOSA FREIRE, ADELINA | E15: 11 | F15: =IFERROR(LOOKUP(E15,CODIGOS!A:A,CODIGOS!B:B)," ") -> OLLA SAN ANTÓN | H15: =IF(J15="SI",IFERROR(LOOKUP(E15,CODIGOS!A:A,CODIGOS!C:C)," "),IFERROR(LOOKUP(E15,CODIGOS!A:A,CODIGOS!D:D),"")) -> 25 | I15: =IFERROR(LOOKUP(C15,SOCIO!A:A,SOCIO!D:D)," ") -> SI | J15: =IFERROR(LOOKUP(D15,SOCIO!B:B,SOCIO!C:C)," ") -> SI
A16: =IF(B16<>0,A15+1," ") -> 15 | B16: 46034 | C16: 3152 | D16: GONZALEZ CASTELLON, RITA BELEN | E16: 2 | F16: =IFERROR(LOOKUP(E16,CODIGOS!A:A,CODIGOS!B:B)," ") -> CUOTA NUEVO SOCIO | H16: =IF(J16="SI",IFERROR(LOOKUP(E16,CODIGOS!A:A,CODIGOS!C:C)," "),IFERROR(LOOKUP(E16,CODIGOS!A:A,CODIGOS!D:D),"")) -> 30 | I16: =IFERROR(LOOKUP(C16,SOCIO!A:A,SOCIO!D:D)," ") -> SI | J16: =IFERROR(LOOKUP(D16,SOCIO!B:B,SOCIO!C:C)," ") -> SI
A17: =IF(B17<>0,A16+1," ") -> 16 | B17: 46034 | C17: 3153 | D17: PEREZ SERRANO, FRANCISCA | E17: 2 | F17: =IFERROR(LOOKUP(E17,CODIGOS!A:A,CODIGOS!B:B)," ") -> CUOTA NUEVO SOCIO | H17: =IF(J17="SI",IFERROR(LOOKUP(E17,CODIGOS!A:A,CODIGOS!C:C)," "),IFERROR(LOOKUP(E17,CODIGOS!A:A,CODIGOS!D:D),"")) -> 30 | I17: =IFERROR(LOOKUP(C17,SOCIO!A:A,SOCIO!D:D)," ") -> SI | J17: =IFERROR(LOOKUP(D17,SOCIO!B:B,SOCIO!C:C)," ") -> SI
A18: =IF(B18<>0,A17+1," ") -> 17 | B18: 46035 | C18: 2900 | D18: MURILLO, HELMER | E18: 10 | F18: =IFERROR(LOOKUP(E18,CODIGOS!A:A,CODIGOS!B:B)," ") -> ÓRGIVA | H18: =IF(J18="SI",IFERROR(LOOKUP(E18,CODIGOS!A:A,CODIGOS!C:C)," "),IFERROR(LOOKUP(E18,CODIGOS!A:A,CODIGOS!D:D),"")) -> 22 | I18: =IFERROR(LOOKUP(C18,SOCIO!A:A,SOCIO!D:D)," ") -> SI | J18: =IFERROR(LOOKUP(D18,SOCIO!B:B,SOCIO!C:C)," ") -> SI
A19: =IF(B19<>0,A18+1," ") -> 18 | B19: 46035 | C19: A/2900 | D19: MURILLO, FLOR | E19: 10 | F19: =IFERROR(LOOKUP(E19,CODIGOS!A:A,CODIGOS!B:B)," ") -> ÓRGIVA | H19: 27 | I19: =IFERROR(LOOKUP(C19,SOCIO!A:A,SOCIO!D:D)," ") | J19: =IFERROR(LOOKUP(D19,SOCIO!B:B,SOCIO!C:C)," ") -> SI
A20: =IF(B20<>0,A19+1," ") -> 19 | B20: 46035 | C20: 2109 | D20: BELTRAN CABRERA, MARILUZ | E20: 10 | F20: =IFERROR(LOOKUP(E20,CODIGOS!A:A,CODIGOS!B:B)," ") -> ÓRGIVA | H20: =IF(J20="SI",IFERROR(LOOKUP(E20,CODIGOS!A:A,CODIGOS!C:C)," "),IFERROR(LOOKUP(E20,CODIGOS!A:A,CODIGOS!D:D),"")) -> 22 | I20: =IFERROR(LOOKUP(C20,SOCIO!A:A,SOCIO!D:D)," ") -> SI | J20: =IFERROR(LOOKUP(D20,SOCIO!B:B,SOCIO!C:C)," ") -> SI
A21: =IF(B21<>0,A20+1," ") -> 20 | B21: 46035 | C21: 2108 | D21: BLASCO AZAUSTRE, MARGARITA | E21: 10 | F21: =IFERROR(LOOKUP(E21,CODIGOS!A:A,CODIGOS!B:B)," ") -> ÓRGIVA | H21: =IF(J21="SI",IFERROR(LOOKUP(E21,CODIGOS!A:A,CODIGOS!C:C)," "),IFERROR(LOOKUP(E21,CODIGOS!A:A,CODIGOS!D:D),"")) -> 22 | I21: =IFERROR(LOOKUP(C21,SOCIO!A:A,SOCIO!D:D)," ") -> SI | J21: =IFERROR(LOOKUP(D21,SOCIO!B:B,SOCIO!C:C)," ") -> SI
A22: =IF(B22<>0,A21+1," ") -> 21 | B22: 46035 | C22: 2109 | D22: BELTRAN CABRERA, MARILUZ | E22: 11 | F22: =IFERROR(LOOKUP(E22,CODIGOS!A:A,CODIGOS!B:B)," ") -> OLLA SAN ANTÓN | H22: =IF(J22="SI",IFERROR(LOOKUP(E22,CODIGOS!A:A,CODIGOS!C:C)," "),IFERROR(LOOKUP(E22,CODIGOS!A:A,CODIGOS!D:D),"")) -> 25 | I22: =IFERROR(LOOKUP(C22,SOCIO!A:A,SOCIO!D:D)," ") -> SI | J22: =IFERROR(LOOKUP(D22,SOCIO!B:B,SOCIO!C:C)," ") -> SI
A23: =IF(B23<>0,A22+1," ") -> 22 | B23: 46035 | C23: 2108 | D23: BLASCO AZAUSTRE, MARGARITA | E23: 11 | F23: =IFERROR(LOOKUP(E23,CODIGOS!A:A,CODIGOS!B:B)," ") -> OLLA SAN ANTÓN | H23: =IF(J23="SI",IFERROR(LOOKUP(E23,CODIGOS!A:A,CODIGOS!C:C)," "),IFERROR(LOOKUP(E23,CODIGOS!A:A,CODIGOS!D:D),"")) -> 25 | I23: =IFERROR(LOOKUP(C23,SOCIO!A:A,SOCIO!D:D)," ") -> SI | J23: =IFERROR(LOOKUP(D23,SOCIO!B:B,SOCIO!C:C)," ") -> SI
A24: =IF(B24<>0,A23+1," ") -> 23 | B24: 46035 | C24: 2900 | D24: MURILLO, HELMER | E24: 12 | F24: =IFERROR(LOOKUP(E24,CODIGOS!A:A,CODIGOS!B:B)," ") -> EXPOSICIÓN CATEDRAL | H24: =IF(J24="SI",IFERROR(LOOKUP(E24,CODIGOS!A:A,CODIGOS!C:C)," "),IFERROR(LOOKUP(E24,CODIGOS!A:A,CODIGOS!D:D),"")) -> 3 | I24: =IFERROR(LOOKUP(C24,SOCIO!A:A,SOCIO!D:D)," ") -> SI | J24: =IFERROR(LOOKUP(D24,SOCIO!B:B,SOCIO!C:C)," ") -> SI
A25: =IF(B25<>0,A24+1," ") -> 24 | B25: 46035 | C25: =IFERROR(LOOKUP(D25,SOCIO!B:B,SOCIO!A:A),"") -> 2709 | D25: MATEOS DELGADO,MERCEDES | E25: 10 | F25: =IFERROR(LOOKUP(E25,CODIGOS!A:A,CODIGOS!B:B)," ") -> ÓRGIVA | H25: =IF(J25="SI",IFERROR(LOOKUP(E25,CODIGOS!A:A,CODIGOS!C:C)," "),IFERROR(LOOKUP(E25,CODIGOS!A:A,CODIGOS!D:D),"")) -> 22 | I25: =IFERROR(LOOKUP(C25,SOCIO!A:A,SOCIO!D:D)," ") -> SI | J25: =IFERROR(LOOKUP(D25,SOCIO!B:B,SOCIO!C:C)," ") -> SI
A26: =IF(B26<>0,A25+1," ") -> 25 | B26: 46035 | C26: 2710 | D26: TORICES VILCHEZ, ANTONIO | E26: 10 | F26: =IFERROR(LOOKUP(E26,CODIGOS!A:A,CODIGOS!B:B)," ") -> ÓRGIVA | H26: =IF(J26="SI",IFERROR(LOOKUP(E26,CODIGOS!A:A,CODIGOS!C:C)," "),IFERROR(LOOKUP(E26,CODIGOS!A:A,CODIGOS!D:D),"")) -> 22 | I26: =IFERROR(LOOKUP(C26,SOCIO!A:A,SOCIO!D:D)," ") -> SI | J26: =IFERROR(LOOKUP(D26,SOCIO!B:B,SOCIO!C:C)," ") -> SI
A27: =IF(B27<>0,A26+1," ") -> 26 | B27: 46035 | C27: 2612 | D27: GALLEGO LORCA, ANTONIO | E27: 10 | F27: =IFERROR(LOOKUP(E27,CODIGOS!A:A,CODIGOS!B:B)," ") -> ÓRGIVA | H27: =IF(J27="SI",IFERROR(LOOKUP(E27,CODIGOS!A:A,CODIGOS!C:C)," "),IFERROR(LOOKUP(E27,CODIGOS!A:A,CODIGOS!D:D),"")) -> 22 | I27: =IFERROR(LOOKUP(C27,SOCIO!A:A,SOCIO!D:D)," ") -> NO | J27: =IFERROR(LOOKUP(D27,SOCIO!B:B,SOCIO!C:C)," ") -> SI
A28: =IF(B28<>0,A27+1," ") -> 27 | B28: 46035 | C28: 2527 | D28: RAMIREZ GARCIA, JOSE ANTONIO | E28: 10 | F28: =IFERROR(LOOKUP(E28,CODIGOS!A:A,CODIGOS!B:B)," ") -> ÓRGIVA | H28: =IF(J28="SI",IFERROR(LOOKUP(E28,CODIGOS!A:A,CODIGOS!C:C)," "),IFERROR(LOOKUP(E28,CODIGOS!A:A,CODIGOS!D:D),"")) -> 22 | I28: =IFERROR(LOOKUP(C28,SOCIO!A:A,SOCIO!D:D)," ") -> NO | J28: =IFERROR(LOOKUP(D28,SOCIO!B:B,SOCIO!C:C)," ") -> SI
A29: =IF(B29<>0,A28+1," ") -> 28 | B29: 46035 | C29: 2553 | D29: PREZ BLANCO, JOSE JOAQUIN | E29: 10 | F29: =IFERROR(LOOKUP(E29,CODIGOS!A:A,CODIGOS!B:B)," ") -> ÓRGIVA | H29: =IF(J29="SI",IFERROR(LOOKUP(E29,CODIGOS!A:A,CODIGOS!C:C)," "),IFERROR(LOOKUP(E29,CODIGOS!A:A,CODIGOS!D:D),"")) -> 22 | I29: =IFERROR(LOOKUP(C29,SOCIO!A:A,SOCIO!D:D)," ") -> NO | J29: =IFERROR(LOOKUP(D29,SOCIO!B:B,SOCIO!C:C)," ") -> SI
A30: =IF(B30<>0,A29+1," ") -> 29 | B30: 46035 | C30: 2817 | D30: GUERRERO BARQUERO, JOSE ANTONIO | E30: 10 | F30: =IFERROR(LOOKUP(E30,CODIGOS!A:A,CODIGOS!B:B)," ") -> ÓRGIVA | H30: =IF(J30="SI",IFERROR(LOOKUP(E30,CODIGOS!A:A,CODIGOS!C:C)," "),IFERROR(LOOKUP(E30,CODIGOS!A:A,CODIGOS!D:D),"")) -> 22 | I30: =IFERROR(LOOKUP(C30,SOCIO!A:A,SOCIO!D:D)," ") -> SI | J30: =IFERROR(LOOKUP(D30,SOCIO!B:B,SOCIO!C:C)," ") -> SI
A31: =IF(B31<>0,A30+1," ") -> 30 | B31: 46035 | C31: 2755 | D31: MORALES GONZALEZ, ISABEL | E31: 10 | F31: =IFERROR(LOOKUP(E31,CODIGOS!A:A,CODIGOS!B:B)," ") -> ÓRGIVA | H31: =IF(J31="SI",IFERROR(LOOKUP(E31,CODIGOS!A:A,CODIGOS!C:C)," "),IFERROR(LOOKUP(E31,CODIGOS!A:A,CODIGOS!D:D),"")) -> 22 | I31: =IFERROR(LOOKUP(C31,SOCIO!A:A,SOCIO!D:D)," ") -> SI | J31: =IFERROR(LOOKUP(D31,SOCIO!B:B,SOCIO!C:C)," ") -> SI
A32: =IF(B32<>0,A31+1," ") -> 31 | B32: 46035 | C32: 2756 | D32: JIMENEZ AGUILAR, ANTONIO | E32: 10 | F32: =IFERROR(LOOKUP(E32,CODIGOS!A:A,CODIGOS!B:B)," ") -> ÓRGIVA | H32: =IF(J32="SI",IFERROR(LOOKUP(E32,CODIGOS!A:A,CODIGOS!C:C)," "),IFERROR(LOOKUP(E32,CODIGOS!A:A,CODIGOS!D:D),"")) -> 22 | I32: =IFERROR(LOOKUP(C32,SOCIO!A:A,SOCIO!D:D)," ") -> SI | J32: =IFERROR(LOOKUP(D32,SOCIO!B:B,SOCIO!C:C)," ") -> SI
A33: =IF(B33<>0,A32+1," ") -> 32 | B33: 46035 | C33: 2764 | D33: JIMENEZ RAMOS, JUAN | E33: 10 | F33: =IFERROR(LOOKUP(E33,CODIGOS!A:A,CODIGOS!B:B)," ") -> ÓRGIVA | H33: =IF(J33="SI",IFERROR(LOOKUP(E33,CODIGOS!A:A,CODIGOS!C:C)," "),IFERROR(LOOKUP(E33,CODIGOS!A:A,CODIGOS!D:D),"")) -> 22 | I33: =IFERROR(LOOKUP(C33,SOCIO!A:A,SOCIO!D:D)," ") -> SI | J33: =IFERROR(LOOKUP(D33,SOCIO!B:B,SOCIO!C:C)," ") -> SI
A34: =IF(B34<>0,A33+1," ") -> 33 | B34: 46035 | C34: 2343 | D34: MONTORO GARCIA, SOFIA | E34: 1 | F34: =IFERROR(LOOKUP(E34,CODIGOS!A:A,CODIGOS!B:B)," ") -> CUOTA SOCIO | H34: 30 | I34: =IFERROR(LOOKUP(C34,SOCIO!A:A,SOCIO!D:D)," ") -> NO | J34: NO
A35: =IF(B35<>0,A34+1," ") -> 34 | B35: 46035 | C35: 1923 | D35: CAÑAVATE FERNANDEZ, INMA | E35: 11 | F35: =IFERROR(LOOKUP(E35,CODIGOS!A:A,CODIGOS!B:B)," ") -> OLLA SAN ANTÓN | H35: =IF(J35="SI",IFERROR(LOOKUP(E35,CODIGOS!A:A,CODIGOS!C:C)," "),IFERROR(LOOKUP(E35,CODIGOS!A:A,CODIGOS!D:D),"")) -> 25 | I35: =IFERROR(LOOKUP(C35,SOCIO!A:A,SOCIO!D:D)," ") -> SI | J35: =IFERROR(LOOKUP(D35,SOCIO!B:B,SOCIO!C:C)," ") -> SI
A36: =IF(B36<>0,A35+1," ") -> 35 | B36: 46035 | C36: 1945 | D36: CAÑAVATE FERNANDEZ, CARMINA | E36: 11 | F36: =IFERROR(LOOKUP(E36,CODIGOS!A:A,CODIGOS!B:B)," ") -> OLLA SAN ANTÓN | H36: =IF(J36="SI",IFERROR(LOOKUP(E36,CODIGOS!A:A,CODIGOS!C:C)," "),IFERROR(LOOKUP(E36,CODIGOS!A:A,CODIGOS!D:D),"")) -> 25 | I36: =IFERROR(LOOKUP(C36,SOCIO!A:A,SOCIO!D:D)," ") -> SI | J36: =IFERROR(LOOKUP(D36,SOCIO!B:B,SOCIO!C:C)," ") -> SI
A37: =IF(B37<>0,A36+1," ") -> 36 | B37: 46035 | C37: 1945 | D37: CAÑAVATE FERNANDEZ, CARMINA | E37: 10 | F37: =IFERROR(LOOKUP(E37,CODIGOS!A:A,CODIGOS!B:B)," ") -> ÓRGIVA | H37: =IF(J37="SI",IFERROR(LOOKUP(E37,CODIGOS!A:A,CODIGOS!C:C)," "),IFERROR(LOOKUP(E37,CODIGOS!A:A,CODIGOS!D:D),"")) -> 22 | I37: =IFERROR(LOOKUP(C37,SOCIO!A:A,SOCIO!D:D)," ") -> SI | J37: =IFERROR(LOOKUP(D37,SOCIO!B:B,SOCIO!C:C)," ") -> SI
A38: =IF(B38<>0,A37+1," ") -> 37 | B38: 46035 | C38: 1923 | D38: CONSUEGRA NAVARRO, JOSE MARIA | E38: 11 | F38: =IFERROR(LOOKUP(E38,CODIGOS!A:A,CODIGOS!B:B)," ") -> OLLA SAN ANTÓN | H38: =IF(J38="SI",IFERROR(LOOKUP(E38,CODIGOS!A:A,CODIGOS!C:C)," "),IFERROR(LOOKUP(E38,CODIGOS!A:A,CODIGOS!D:D),"")) -> 25 | I38: =IFERROR(LOOKUP(C38,SOCIO!A:A,SOCIO!D:D)," ") -> SI | J38: =IFERROR(LOOKUP(D38,SOCIO!B:B,SOCIO!C:C)," ") -> SI
A39: =IF(B39<>0,A38+1," ") -> 38 | B39: 46035 | C39: 1923 | D39: CONSUEGRA NAVARRO, JOSE MARIA | E39: 10 | F39: =IFERROR(LOOKUP(E39,CODIGOS!A:A,CODIGOS!B:B)," ") -> ÓRGIVA | H39: =IF(J39="SI",IFERROR(LOOKUP(E39,CODIGOS!A:A,CODIGOS!C:C)," "),IFERROR(LOOKUP(E39,CODIGOS!A:A,CODIGOS!D:D),"")) -> 22 | I39: =IFERROR(LOOKUP(C39,SOCIO!A:A,SOCIO!D:D)," ") -> SI | J39: =IFERROR(LOOKUP(D39,SOCIO!B:B,SOCIO!C:C)," ") -> SI
A40: =IF(B40<>0,A39+1," ") -> 39 | B40: 46035 | C40: 2219 | D40: CANO SANCHEZ, CARMEN | E40: 1 | F40: =IFERROR(LOOKUP(E40,CODIGOS!A:A,CODIGOS!B:B)," ") -> CUOTA SOCIO | H40: =IF(J40="SI",IFERROR(LOOKUP(E40,CODIGOS!A:A,CODIGOS!C:C)," "),IFERROR(LOOKUP(E40,CODIGOS!A:A,CODIGOS!D:D),"")) -> 30 | I40: =IFERROR(LOOKUP(C40,SOCIO!A:A,SOCIO!D:D)," ") -> NO | J40: =IFERROR(LOOKUP(D40,SOCIO!B:B,SOCIO!C:C)," ") -> SI
A41: =IF(B41<>0,A40+1," ") -> 40 | B41: 46035 | C41: =IFERROR(LOOKUP(D41,SOCIO!B:B,SOCIO!A:A),"") -> 2310 | D41: VELA DE LA TORRE, MANUEL | E41: 11 | F41: =IFERROR(LOOKUP(E41,CODIGOS!A:A,CODIGOS!B:B)," ") -> OLLA SAN ANTÓN | H41: =IF(J41="SI",IFERROR(LOOKUP(E41,CODIGOS!A:A,CODIGOS!C:C)," "),IFERROR(LOOKUP(E41,CODIGOS!A:A,CODIGOS!D:D),"")) -> 25 | I41: =IFERROR(LOOKUP(C41,SOCIO!A:A,SOCIO!D:D)," ") -> NO | J41: =IFERROR(LOOKUP(D41,SOCIO!B:B,SOCIO!C:C)," ") -> SI
A42: =IF(B42<>0,A41+1," ") -> 41 | B42: 46035 | C42: =IFERROR(LOOKUP(D42,SOCIO!B:B,SOCIO!A:A),"") -> 1433 | D42: RODRÍGUEZ SÁNCHEZ, JOSÉ | E42: 11 | F42: =IFERROR(LOOKUP(E42,CODIGOS!A:A,CODIGOS!B:B)," ") -> OLLA SAN ANTÓN | H42: =IF(J42="SI",IFERROR(LOOKUP(E42,CODIGOS!A:A,CODIGOS!C:C)," "),IFERROR(LOOKUP(E42,CODIGOS!A:A,CODIGOS!D:D),"")) -> 25 | I42: =IFERROR(LOOKUP(C42,SOCIO!A:A,SOCIO!D:D)," ") -> NO | J42: =IFERROR(LOOKUP(D42,SOCIO!B:B,SOCIO!C:C)," ") -> SI
A43: =IF(B43<>0,A42+1," ") -> 42 | B43: 46035 | C43: A/1433 | D43: DOMÍNGUEZ MONTORO ANA | E43: 11 | F43: =IFERROR(LOOKUP(E43,CODIGOS!A:A,CODIGOS!B:B)," ") -> OLLA SAN ANTÓN | H43: 30 | I43: =IFERROR(LOOKUP(C43,SOCIO!A:A,SOCIO!D:D)," ") | J43: =IFERROR(LOOKUP(D43,SOCIO!B:B,SOCIO!C:C)," ") -> SI
A44: =IF(B44<>0,A43+1," ") -> 43 | B44: 46035 | C44: =IFERROR(LOOKUP(D44,SOCIO!B:B,SOCIO!A:A),"") -> 1433 | D44: RODRÍGUEZ SÁNCHEZ, JOSÉ | E44: 12 | F44: =IFERROR(LOOKUP(E44,CODIGOS!A:A,CODIGOS!B:B)," ") -> EXPOSICIÓN CATEDRAL | H44: =IF(J44="SI",IFERROR(LOOKUP(E44,CODIGOS!A:A,CODIGOS!C:C)," "),IFERROR(LOOKUP(E44,CODIGOS!A:A,CODIGOS!D:D),"")) -> 3 | I44: =IFERROR(LOOKUP(C44,SOCIO!A:A,SOCIO!D:D)," ") -> NO | J44: =IFERROR(LOOKUP(D44,SOCIO!B:B,SOCIO!C:C)," ") -> SI
A45: =IF(B45<>0,A44+1," ") -> 44 | B45: 46035 | C45: A/1433 | D45: DOMÍNGUEZ MONTORO ANA | E45: 12 | F45: =IFERROR(LOOKUP(E45,CODIGOS!A:A,CODIGOS!B:B)," ") -> EXPOSICIÓN CATEDRAL | H45: =IF(J45="SI",IFERROR(LOOKUP(E45,CODIGOS!A:A,CODIGOS!C:C)," "),IFERROR(LOOKUP(E45,CODIGOS!A:A,CODIGOS!D:D),"")) -> 3 | I45: =IFERROR(LOOKUP(C45,SOCIO!A:A,SOCIO!D:D)," ") | J45: =IFERROR(LOOKUP(D45,SOCIO!B:B,SOCIO!C:C)," ") -> SI
A46: =IF(B46<>0,A45+1," ") -> 45 | B46: 46035 | C46: =IFERROR(LOOKUP(D46,SOCIO!B:B,SOCIO!A:A),"") -> 2563 | D46: MARTIN PEÑA, VICTORIANO | E46: 11 | F46: =IFERROR(LOOKUP(E46,CODIGOS!A:A,CODIGOS!B:B)," ") -> OLLA SAN ANTÓN | H46: =IF(J46="SI",IFERROR(LOOKUP(E46,CODIGOS!A:A,CODIGOS!C:C)," "),IFERROR(LOOKUP(E46,CODIGOS!A:A,CODIGOS!D:D),"")) -> 25 | I46: =IFERROR(LOOKUP(C46,SOCIO!A:A,SOCIO!D:D)," ") -> NO | J46: =IFERROR(LOOKUP(D46,SOCIO!B:B,SOCIO!C:C)," ") -> SI
A47: =IF(B47<>0,A46+1," ") -> 46 | B47: 46035 | C47: =IFERROR(LOOKUP(D47,SOCIO!B:B,SOCIO!A:A),"") -> 3154 | D47: SÁNCHEZ DOMINGO, MARILUZ | E47: 2 | F47: =IFERROR(LOOKUP(E47,CODIGOS!A:A,CODIGOS!B:B)," ") -> CUOTA NUEVO SOCIO | H47: 30 | I47: =IFERROR(LOOKUP(C47,SOCIO!A:A,SOCIO!D:D)," ") -> SI | J47: SI
A48: =IF(B48<>0,A47+1," ") -> 47 | B48: 46035 | C48: =IFERROR(LOOKUP(D48,SOCIO!B:B,SOCIO!A:A),"") -> 3155 | D48: SÁNCHEZ GARCÍA, MARIA LUISA | E48: 2 | F48: =IFERROR(LOOKUP(E48,CODIGOS!A:A,CODIGOS!B:B)," ") -> CUOTA NUEVO SOCIO | H48: 30 | I48: =IFERROR(LOOKUP(C48,SOCIO!A:A,SOCIO!D:D)," ") -> SI | J48: SI
A49: =IF(B49<>0,A48+1," ") -> 48 | B49: 46036 | C49: =IFERROR(LOOKUP(D49,SOCIO!B:B,SOCIO!A:A),"") -> 2596 | D49: OLIVER BARRIONUEVO, MERCEDES | E49: 11 | F49: =IFERROR(LOOKUP(E49,CODIGOS!A:A,CODIGOS!B:B)," ") -> OLLA SAN ANTÓN | H49: 25 | I49: =IFERROR(LOOKUP(C49,SOCIO!A:A,SOCIO!D:D)," ") -> NO | J49: =IFERROR(LOOKUP(D49,SOCIO!B:B,SOCIO!C:C)," ") -> SI
A50: =IF(B50<>0,A49+1," ") -> 49 | B50: 46036 | C50: =IFERROR(LOOKUP(D50,SOCIO!B:B,SOCIO!A:A),"") -> 2930 | D50: SALAS GARCÍA, TOÑI | E50: 4 | F50: =IFERROR(LOOKUP(E50,CODIGOS!A:A,CODIGOS!B:B)," ") -> DEVOLUCION | H50: -45 | I50: =IFERROR(LOOKUP(C50,SOCIO!A:A,SOCIO!D:D)," ") -> SI | J50: =IFERROR(LOOKUP(D50,SOCIO!B:B,SOCIO!C:C)," ") -> SI
A51: =IF(B51<>0,A50+1," ") -> 50 | B51: 46036 | C51: =IFERROR(LOOKUP(D51,SOCIO!B:B,SOCIO!A:A),"") -> 1920 | D51: HERAS JIMENEZ, JOSE FRANCISCO | E51: 4 | F51: =IFERROR(LOOKUP(E51,CODIGOS!A:A,CODIGOS!B:B)," ") -> DEVOLUCION | H51: -22 | I51: =IFERROR(LOOKUP(C51,SOCIO!A:A,SOCIO!D:D)," ") -> SI | J51: =IFERROR(LOOKUP(D51,SOCIO!B:B,SOCIO!C:C)," ") -> SI
A52: =IF(B52<>0,A51+1," ") -> 51 | B52: 46041 | C52: 2456 | D52: TELLEZ SANCHEZ, SEBASTIAN | E52: 13 | F52: =IFERROR(LOOKUP(E52,CODIGOS!A:A,CODIGOS!B:B)," ") -> ENSAYO ORQUESTA | H52: =IF(J52="SI",IFERROR(LOOKUP(E52,CODIGOS!A:A,CODIGOS!C:C)," "),IFERROR(LOOKUP(E52,CODIGOS!A:A,CODIGOS!D:D),"")) -> 0 | I52: =IFERROR(LOOKUP(C52,SOCIO!A:A,SOCIO!D:D)," ") -> SI | J52: =IFERROR(LOOKUP(D52,SOCIO!B:B,SOCIO!C:C)," ") -> SI
A53: =IF(B53<>0,A52+1," ") -> 52 | B53: 46041 | C53: =IFERROR(LOOKUP(D53,SOCIO!B:B,SOCIO!A:A),"") -> 2414 | D53: GARCIA GOMEZ, FRANCISCA | E53: 13 | F53: =IFERROR(LOOKUP(E53,CODIGOS!A:A,CODIGOS!B:B)," ") -> ENSAYO ORQUESTA | H53: =IF(J53="SI",IFERROR(LOOKUP(E53,CODIGOS!A:A,CODIGOS!C:C)," "),IFERROR(LOOKUP(E53,CODIGOS!A:A,CODIGOS!D:D),"")) -> 0 | I53: =IFERROR(LOOKUP(C53,SOCIO!A:A,SOCIO!D:D)," ") -> SI | J53: =IFERROR(LOOKUP(D53,SOCIO!B:B,SOCIO!C:C)," ") -> SI
A54: =IF(B54<>0,A53+1," ") -> 53 | B54: 46042 | C54: =IFERROR(LOOKUP(D54,SOCIO!B:B,SOCIO!A:A),"") -> 2004 | D54: MANGAS MACÍAS, FRANCIS | E54: 11 | F54: =IFERROR(LOOKUP(E54,CODIGOS!A:A,CODIGOS!B:B)," ") -> OLLA SAN ANTÓN | H54: =IF(J54="SI",IFERROR(LOOKUP(E54,CODIGOS!A:A,CODIGOS!C:C)," "),IFERROR(LOOKUP(E54,CODIGOS!A:A,CODIGOS!D:D),"")) -> 25 | I54: =IFERROR(LOOKUP(C54,SOCIO!A:A,SOCIO!D:D)," ") -> SI | J54: =IFERROR(LOOKUP(D54,SOCIO!B:B,SOCIO!C:C)," ") -> SI
A55: =IF(B55<>0,A54+1," ") -> 54 | B55: 46042 | C55: =IFERROR(LOOKUP(D55,SOCIO!B:B,SOCIO!A:A),"") -> 2003 | D55: SORIANO PARRA, CARMEN | E55: 11 | F55: =IFERROR(LOOKUP(E55,CODIGOS!A:A,CODIGOS!B:B)," ") -> OLLA SAN ANTÓN | H55: =IF(J55="SI",IFERROR(LOOKUP(E55,CODIGOS!A:A,CODIGOS!C:C)," "),IFERROR(LOOKUP(E55,CODIGOS!A:A,CODIGOS!D:D),"")) -> 25 | I55: =IFERROR(LOOKUP(C55,SOCIO!A:A,SOCIO!D:D)," ") -> SI | J55: =IFERROR(LOOKUP(D55,SOCIO!B:B,SOCIO!C:C)," ") -> SI
A56: =IF(B56<>0,A55+1," ") -> 55 | B56: 46042 | C56: =IFERROR(LOOKUP(D56,SOCIO!B:B,SOCIO!A:A),"") -> 2084 | D56: RODRIGUEZ AZNARTE, ANA CARMEN | E56: 11 | F56: =IFERROR(LOOKUP(E56,CODIGOS!A:A,CODIGOS!B:B)," ") -> OLLA SAN ANTÓN | H56: =IF(J56="SI",IFERROR(LOOKUP(E56,CODIGOS!A:A,CODIGOS!C:C)," "),IFERROR(LOOKUP(E56,CODIGOS!A:A,CODIGOS!D:D),"")) -> 25 | I56: =IFERROR(LOOKUP(C56,SOCIO!A:A,SOCIO!D:D)," ") -> SI | J56: =IFERROR(LOOKUP(D56,SOCIO!B:B,SOCIO!C:C)," ") -> SI
A57: =IF(B57<>0,A56+1," ") -> 56 | B57: 46042 | C57: =IFERROR(LOOKUP(D57,SOCIO!B:B,SOCIO!A:A),"") -> 1930 | D57: CORRALES CARRETERO, MANUEL | E57: 10 | F57: =IFERROR(LOOKUP(E57,CODIGOS!A:A,CODIGOS!B:B)," ") -> ÓRGIVA | H57: =IF(J57="SI",IFERROR(LOOKUP(E57,CODIGOS!A:A,CODIGOS!C:C)," "),IFERROR(LOOKUP(E57,CODIGOS!A:A,CODIGOS!D:D),"")) -> 22 | I57: =IFERROR(LOOKUP(C57,SOCIO!A:A,SOCIO!D:D)," ") -> SI | J57: =IFERROR(LOOKUP(D57,SOCIO!B:B,SOCIO!C:C)," ") -> SI
A58: =IF(B58<>0,A57+1," ") -> 57 | B58: 46042 | C58: =IFERROR(LOOKUP(D58,SOCIO!B:B,SOCIO!A:A),"") -> 2004 | D58: MANGAS MACÍAS, FRANCIS | E58: 10 | F58: =IFERROR(LOOKUP(E58,CODIGOS!A:A,CODIGOS!B:B)," ") -> ÓRGIVA | H58: =IF(J58="SI",IFERROR(LOOKUP(E58,CODIGOS!A:A,CODIGOS!C:C)," "),IFERROR(LOOKUP(E58,CODIGOS!A:A,CODIGOS!D:D),"")) -> 22 | I58: =IFERROR(LOOKUP(C58,SOCIO!A:A,SOCIO!D:D)," ") -> SI | J58: =IFERROR(LOOKUP(D58,SOCIO!B:B,SOCIO!C:C)," ") -> SI
A59: =IF(B59<>0,A58+1," ") -> 58 | B59: 46042 | C59: =IFERROR(LOOKUP(D59,SOCIO!B:B,SOCIO!A:A),"") -> 2003 | D59: SORIANO PARRA, CARMEN | E59: 10 | F59: =IFERROR(LOOKUP(E59,CODIGOS!A:A,CODIGOS!B:B)," ") -> ÓRGIVA | H59: =IF(J59="SI",IFERROR(LOOKUP(E59,CODIGOS!A:A,CODIGOS!C:C)," "),IFERROR(LOOKUP(E59,CODIGOS!A:A,CODIGOS!D:D),"")) -> 22 | I59: =IFERROR(LOOKUP(C59,SOCIO!A:A,SOCIO!D:D)," ") -> SI | J59: =IFERROR(LOOKUP(D59,SOCIO!B:B,SOCIO!C:C)," ") -> SI
A60: =IF(B60<>0,A59+1," ") -> 59 | B60: 46042 | C60: =IFERROR(LOOKUP(D60,SOCIO!B:B,SOCIO!A:A),"") -> 3140 | D60: RUIZ SANCHEZ, MARIA MERCEDES | E60: 14 | F60: =IFERROR(LOOKUP(E60,CODIGOS!A:A,CODIGOS!B:B)," ") -> BASÍLICA DE SAN JUAN DE DIOS | H60: =IF(J60="SI",IFERROR(LOOKUP(E60,CODIGOS!A:A,CODIGOS!C:C)," "),IFERROR(LOOKUP(E60,CODIGOS!A:A,CODIGOS!D:D),"")) -> 5 | I60: =IFERROR(LOOKUP(C60,SOCIO!A:A,SOCIO!D:D)," ") -> SI | J60: =IFERROR(LOOKUP(D60,SOCIO!B:B,SOCIO!C:C)," ") -> SI
A61: =IF(B61<>0,A60+1," ") -> 60 | B61: 46042 | C61: =IFERROR(LOOKUP(D61,SOCIO!B:B,SOCIO!A:A),"") -> 1030 | D61: ALCALDE CASTILLA, ANTONIO | E61: 10 | F61: =IFERROR(LOOKUP(E61,CODIGOS!A:A,CODIGOS!B:B)," ") -> ÓRGIVA | H61: =IF(J61="SI",IFERROR(LOOKUP(E61,CODIGOS!A:A,CODIGOS!C:C)," "),IFERROR(LOOKUP(E61,CODIGOS!A:A,CODIGOS!D:D),"")) -> 22 | I61: =IFERROR(LOOKUP(C61,SOCIO!A:A,SOCIO!D:D)," ") -> NO | J61: =IFERROR(LOOKUP(D61,SOCIO!B:B,SOCIO!C:C)," ") -> SI
A62: =IF(B62<>0,A61+1," ") -> 61 | B62: 46042 | C62: =IFERROR(LOOKUP(D62,SOCIO!B:B,SOCIO!A:A),"") -> 1581 | D62: ESTEVEZ MARQUEZ, MARIA DE CARMEN | E62: 10 | F62: =IFERROR(LOOKUP(E62,CODIGOS!A:A,CODIGOS!B:B)," ") -> ÓRGIVA | H62: =IF(J62="SI",IFERROR(LOOKUP(E62,CODIGOS!A:A,CODIGOS!C:C)," "),IFERROR(LOOKUP(E62,CODIGOS!A:A,CODIGOS!D:D),"")) -> 22 | I62: =IFERROR(LOOKUP(C62,SOCIO!A:A,SOCIO!D:D)," ") -> NO | J62: =IFERROR(LOOKUP(D62,SOCIO!B:B,SOCIO!C:C)," ") -> SI
A63: =IF(B63<>0,A62+1," ") -> 62 | B63: 46042 | C63: =IFERROR(LOOKUP(D63,SOCIO!B:B,SOCIO!A:A),"") -> 3004 | D63: MUÑOZ GARZÓN, Mª CARMEN | E63: 14 | F63: =IFERROR(LOOKUP(E63,CODIGOS!A:A,CODIGOS!B:B)," ") -> BASÍLICA DE SAN JUAN DE DIOS | H63: =IF(J63="SI",IFERROR(LOOKUP(E63,CODIGOS!A:A,CODIGOS!C:C)," "),IFERROR(LOOKUP(E63,CODIGOS!A:A,CODIGOS!D:D),"")) -> 5 | I63: =IFERROR(LOOKUP(C63,SOCIO!A:A,SOCIO!D:D)," ") -> SI | J63: =IFERROR(LOOKUP(D63,SOCIO!B:B,SOCIO!C:C)," ") -> SI
A64: =IF(B64<>0,A63+1," ") -> 63 | B64: 46043 | C64: =IFERROR(LOOKUP(D64,SOCIO!B:B,SOCIO!A:A),"") -> 1930 | D64: CORRALES CARRETERO, MANUEL | E64: 14 | F64: =IFERROR(LOOKUP(E64,CODIGOS!A:A,CODIGOS!B:B)," ") -> BASÍLICA DE SAN JUAN DE DIOS | H64: =IF(J64="SI",IFERROR(LOOKUP(E64,CODIGOS!A:A,CODIGOS!C:C)," "),IFERROR(LOOKUP(E64,CODIGOS!A:A,CODIGOS!D:D),"")) -> 5 | I64: =IFERROR(LOOKUP(C64,SOCIO!A:A,SOCIO!D:D)," ") -> SI | J64: =IFERROR(LOOKUP(D64,SOCIO!B:B,SOCIO!C:C)," ") -> SI
... A67: =IF(B67<>0,A66+1," ") -> 66 | B67: 46043 | C67: =IFERROR(LOOKUP(D67,SOCIO!B:B,SOCIO!A:A),"") -> 2003 | D67: SORIANO PARRA, CARMEN | E67: 14 | F67: =IFERROR(LOOKUP(E67,CODIGOS!A:A,CODIGOS!B:B)," ") -> BASÍLICA DE SAN JUAN DE DIOS | H67: =IF(J67="SI",IFERROR(LOOKUP(E67,CODIGOS!A:A,CODIGOS!C:C)," "),IFERROR(LOOKUP(E67,CODIGOS!A:A,CODIGOS!D:D),"")) -> 5 | I67: =IFERROR(LOOKUP(C67,SOCIO!A:A,SOCIO!D:D)," ") -> SI | J67: =IFERROR(LOOKUP(D67,SOCIO!B:B,SOCIO!C:C)," ") -> SI
A68: =IF(B68<>0,A67+1," ") -> 67 | B68: 46043 | C68: 2969 | D68: RANZ CHACOBO, ANGEL | E68: 15 | F68: =IFERROR(LOOKUP(E68,CODIGOS!A:A,CODIGOS!B:B)," ") -> MUSEO SAN JUAN DE DIOS CP | H68: 5 | I68: =IFERROR(LOOKUP(C68,SOCIO!A:A,SOCIO!D:D)," ") -> SI | J68: SI
A69: =IF(B69<>0,A68+1," ") -> 68 | B69: 46043 | C69: 3108 | D69: MORON GALLARDO,TERESA | E69: 14 | F69: =IFERROR(LOOKUP(E69,CODIGOS!A:A,CODIGOS!B:B)," ") -> BASÍLICA DE SAN JUAN DE DIOS | H69: =IF(J69="SI",IFERROR(LOOKUP(E69,CODIGOS!A:A,CODIGOS!C:C)," "),IFERROR(LOOKUP(E69,CODIGOS!A:A,CODIGOS!D:D),"")) -> 5 | I69: =IFERROR(LOOKUP(C69,SOCIO!A:A,SOCIO!D:D)," ") -> SI | J69: =IFERROR(LOOKUP(D69,SOCIO!B:B,SOCIO!C:C)," ") -> SI
A70: =IF(B70<>0,A69+1," ") -> 69 | B70: 46043 | C70: 3108 | D70: MORON GALLARDO,TERESA | E70: 15 | F70: =IFERROR(LOOKUP(E70,CODIGOS!A:A,CODIGOS!B:B)," ") -> MUSEO SAN JUAN DE DIOS CP | H70: =IF(J70="SI",IFERROR(LOOKUP(E70,CODIGOS!A:A,CODIGOS!C:C)," "),IFERROR(LOOKUP(E70,CODIGOS!A:A,CODIGOS!D:D),"")) -> 5 | I70: =IFERROR(LOOKUP(C70,SOCIO!A:A,SOCIO!D:D)," ") -> SI | J70: =IFERROR(LOOKUP(D70,SOCIO!B:B,SOCIO!C:C)," ") -> SI
A71: =IF(B71<>0,A70+1," ") -> 70 | B71: 46043 | C71: 2913 | D71: BERBEL GARCIA, MARIA ISABEL | E71: 2 | F71: =IFERROR(LOOKUP(E71,CODIGOS!A:A,CODIGOS!B:B)," ") -> CUOTA NUEVO SOCIO | H71: =IF(J71="SI",IFERROR(LOOKUP(E71,CODIGOS!A:A,CODIGOS!C:C)," "),IFERROR(LOOKUP(E71,CODIGOS!A:A,CODIGOS!D:D),"")) -> 30 | I71: =IFERROR(LOOKUP(C71,SOCIO!A:A,SOCIO!D:D)," ") -> SI | J71: =IFERROR(LOOKUP(D71,SOCIO!B:B,SOCIO!C:C)," ") -> SI
A72: =IF(B72<>0,A71+1," ") -> 71 | B72: 46043 | C72: =IFERROR(LOOKUP(D72,SOCIO!B:B,SOCIO!A:A),"") -> 1823 | D72: CAÑAVATE FERNANDEZ, MARIA CONCEPCION | E72: 10 | F72: =IFERROR(LOOKUP(E72,CODIGOS!A:A,CODIGOS!B:B)," ") -> ÓRGIVA | H72: =IF(J72="SI",IFERROR(LOOKUP(E72,CODIGOS!A:A,CODIGOS!C:C)," "),IFERROR(LOOKUP(E72,CODIGOS!A:A,CODIGOS!D:D),"")) -> 22 | I72: =IFERROR(LOOKUP(C72,SOCIO!A:A,SOCIO!D:D)," ") -> SI | J72: =IFERROR(LOOKUP(D72,SOCIO!B:B,SOCIO!C:C)," ") -> SI
A73: =IF(B73<>0,A72+1," ") -> 72 | B73: 46043 | C73: =IFERROR(LOOKUP(D73,SOCIO!B:B,SOCIO!A:A),"") -> 1920 | D73: HERAS JIMENEZ, JOSE FRANCISCO | E73: 11 | F73: =IFERROR(LOOKUP(E73,CODIGOS!A:A,CODIGOS!B:B)," ") -> OLLA SAN ANTÓN | H73: =IF(J73="SI",IFERROR(LOOKUP(E73,CODIGOS!A:A,CODIGOS!C:C)," "),IFERROR(LOOKUP(E73,CODIGOS!A:A,CODIGOS!D:D),"")) -> 25 | I73: =IFERROR(LOOKUP(C73,SOCIO!A:A,SOCIO!D:D)," ") -> SI | J73: =IFERROR(LOOKUP(D73,SOCIO!B:B,SOCIO!C:C)," ") -> SI
A74: =IF(B74<>0,A73+1," ") -> 73 | B74: 46048 | C74: =IFERROR(LOOKUP(D74,SOCIO!B:B,SOCIO!A:A),"") -> 3156 | D74: MORENTE MUÑOZ, MARIA LUISA | E74: 2 | F74: =IFERROR(LOOKUP(E74,CODIGOS!A:A,CODIGOS!B:B)," ") -> CUOTA NUEVO SOCIO | H74: =IF(J74="SI",IFERROR(LOOKUP(E74,CODIGOS!A:A,CODIGOS!C:C)," "),IFERROR(LOOKUP(E74,CODIGOS!A:A,CODIGOS!D:D),"")) -> 30 | I74: =IFERROR(LOOKUP(C74,SOCIO!A:A,SOCIO!D:D)," ") -> SI | J74: =IFERROR(LOOKUP(D74,SOCIO!B:B,SOCIO!C:C)," ") -> SI
A75: =IF(B75<>0,A74+1," ") -> 74 | B75: 46048 | C75: 3157 | D75: MAÑOSA TEJADA, MAGDALENA | E75: 2 | F75: =IFERROR(LOOKUP(E75,CODIGOS!A:A,CODIGOS!B:B)," ") -> CUOTA NUEVO SOCIO | H75: =IF(J75="SI",IFERROR(LOOKUP(E75,CODIGOS!A:A,CODIGOS!C:C)," "),IFERROR(LOOKUP(E75,CODIGOS!A:A,CODIGOS!D:D),"")) -> 30 | I75: =IFERROR(LOOKUP(C75,SOCIO!A:A,SOCIO!D:D)," ") -> SI | J75: =IFERROR(LOOKUP(D75,SOCIO!B:B,SOCIO!C:C)," ") -> SI
A76: =IF(B76<>0,A75+1," ") -> 75 | B76: 46048 | C76: 3158 | D76: ENTRENA MUÑOZ, PURIFICACIÓN | E76: 2 | F76: =IFERROR(LOOKUP(E76,CODIGOS!A:A,CODIGOS!B:B)," ") -> CUOTA NUEVO SOCIO | H76: =IF(J76="SI",IFERROR(LOOKUP(E76,CODIGOS!A:A,CODIGOS!C:C)," "),IFERROR(LOOKUP(E76,CODIGOS!A:A,CODIGOS!D:D),"")) -> 30 | I76: =IFERROR(LOOKUP(C76,SOCIO!A:A,SOCIO!D:D)," ") -> SI | J76: =IFERROR(LOOKUP(D76,SOCIO!B:B,SOCIO!C:C)," ") -> SI
A77: =IF(B77<>0,A76+1," ") -> 76 | B77: 46042 | C77: 3159 | D77: CUELLO MELGAREJO, SANTIAGO | E77: 2 | F77: =IFERROR(LOOKUP(E77,CODIGOS!A:A,CODIGOS!B:B)," ") -> CUOTA NUEVO SOCIO | H77: =IF(J77="SI",IFERROR(LOOKUP(E77,CODIGOS!A:A,CODIGOS!C:C)," "),IFERROR(LOOKUP(E77,CODIGOS!A:A,CODIGOS!D:D),"")) -> 30 | I77: =IFERROR(LOOKUP(C77,SOCIO!A:A,SOCIO!D:D)," ") -> SI | J77: =IFERROR(LOOKUP(D77,SOCIO!B:B,SOCIO!C:C)," ") -> SI
A78: =IF(B78<>0,A77+1," ") -> 77 | B78: 46048 | C78: 3160 | D78: RUBIO CASTRO, ESTELA | E78: 2 | F78: =IFERROR(LOOKUP(E78,CODIGOS!A:A,CODIGOS!B:B)," ") -> CUOTA NUEVO SOCIO | H78: =IF(J78="SI",IFERROR(LOOKUP(E78,CODIGOS!A:A,CODIGOS!C:C)," "),IFERROR(LOOKUP(E78,CODIGOS!A:A,CODIGOS!D:D),"")) -> 30 | I78: =IFERROR(LOOKUP(C78,SOCIO!A:A,SOCIO!D:D)," ") -> SI | J78: =IFERROR(LOOKUP(D78,SOCIO!B:B,SOCIO!C:C)," ") -> SI
A79: =IF(B79<>0,A78+1," ") -> 78 | B79: 46049 | C79: =IFERROR(LOOKUP(D79,SOCIO!B:B,SOCIO!A:A),"") -> 1930 | D79: CORRALES CARRETERO, MANUEL | E79: 4 | F79: =IFERROR(LOOKUP(E79,CODIGOS!A:A,CODIGOS!B:B)," ") -> DEVOLUCION | G79: ORGIVA | H79: -22 | I79: =IFERROR(LOOKUP(C79,SOCIO!A:A,SOCIO!D:D)," ") -> SI | J79: =IFERROR(LOOKUP(D79,SOCIO!B:B,SOCIO!C:C)," ") -> SI
A80: =IF(B80<>0,A79+1," ") -> 79 | B80: 46049 | C80: =IFERROR(LOOKUP(D80,SOCIO!B:B,SOCIO!A:A),"") -> 2004 | D80: MANGAS MACÍAS, FRANCIS | E80: 4 | F80: =IFERROR(LOOKUP(E80,CODIGOS!A:A,CODIGOS!B:B)," ") -> DEVOLUCION | G80: ORGIVA | H80: -22 | I80: =IFERROR(LOOKUP(C80,SOCIO!A:A,SOCIO!D:D)," ") -> SI | J80: =IFERROR(LOOKUP(D80,SOCIO!B:B,SOCIO!C:C)," ") -> SI
A81: =IF(B81<>0,A80+1," ") -> 80 | B81: 46049 | C81: =IFERROR(LOOKUP(D81,SOCIO!B:B,SOCIO!A:A),"") -> 2003 | D81: SORIANO PARRA, CARMEN | E81: 4 | F81: =IFERROR(LOOKUP(E81,CODIGOS!A:A,CODIGOS!B:B)," ") -> DEVOLUCION | G81: ORGIVA | H81: -22 | I81: =IFERROR(LOOKUP(C81,SOCIO!A:A,SOCIO!D:D)," ") -> SI | J81: =IFERROR(LOOKUP(D81,SOCIO!B:B,SOCIO!C:C)," ") -> SI
A82: =IF(B82<>0,A81+1," ") -> 81 | B82: 46049 | C82: =IFERROR(LOOKUP(D82,SOCIO!B:B,SOCIO!A:A),"") -> 2004 | D82: MANGAS MACÍAS, FRANCIS | E82: 4 | F82: =IFERROR(LOOKUP(E82,CODIGOS!A:A,CODIGOS!B:B)," ") -> DEVOLUCION | G82: SAN JD | H82: -5 | I82: =IFERROR(LOOKUP(C82,SOCIO!A:A,SOCIO!D:D)," ") -> SI | J82: =IFERROR(LOOKUP(D82,SOCIO!B:B,SOCIO!C:C)," ") -> SI
A83: =IF(B83<>0,A82+1," ") -> 82 | B83: 46049 | C83: =IFERROR(LOOKUP(D83,SOCIO!B:B,SOCIO!A:A),"") -> 2003 | D83: SORIANO PARRA, CARMEN | E83: 4 | F83: =IFERROR(LOOKUP(E83,CODIGOS!A:A,CODIGOS!B:B)," ") -> DEVOLUCION | G83: SAN JD | H83: -5 | I83: =IFERROR(LOOKUP(C83,SOCIO!A:A,SOCIO!D:D)," ") -> SI | J83: =IFERROR(LOOKUP(D83,SOCIO!B:B,SOCIO!C:C)," ") -> SI
A84: =IF(B84<>0,A83+1," ") -> 83 | B84: 46049 | C84: =IFERROR(LOOKUP(D84,SOCIO!B:B,SOCIO!A:A),"") -> 3004 | D84: MUÑOZ GARZÓN, Mª CARMEN | E84: 4 | F84: =IFERROR(LOOKUP(E84,CODIGOS!A:A,CODIGOS!B:B)," ") -> DEVOLUCION | G84: SAN JD | H84: -5 | I84: =IFERROR(LOOKUP(C84,SOCIO!A:A,SOCIO!D:D)," ") -> SI | J84: =IFERROR(LOOKUP(D84,SOCIO!B:B,SOCIO!C:C)," ") -> SI
A85: =IF(B85<>0,A84+1," ") -> 84 | B85: 46049 | C85: =IFERROR(LOOKUP(D85,SOCIO!B:B,SOCIO!A:A),"") -> 1930 | D85: CORRALES CARRETERO, MANUEL | E85: 16 | F85: =IFERROR(LOOKUP(E85,CODIGOS!A:A,CODIGOS!B:B)," ") -> LA CARTUJA | H85: =IF(J85="SI",IFERROR(LOOKUP(E85,CODIGOS!A:A,CODIGOS!C:C)," "),IFERROR(LOOKUP(E85,CODIGOS!A:A,CODIGOS!D:D),"")) -> 7 | I85: =IFERROR(LOOKUP(C85,SOCIO!A:A,SOCIO!D:D)," ") -> SI | J85: =IFERROR(LOOKUP(D85,SOCIO!B:B,SOCIO!C:C)," ") -> SI
A86: =IF(B86<>0,A85+1," ") -> 85 | B86: 46049 | C86: =IFERROR(LOOKUP(D86,SOCIO!B:B,SOCIO!A:A),"") -> 2004 | D86: MANGAS MACÍAS, FRANCIS | E86: 16 | F86: =IFERROR(LOOKUP(E86,CODIGOS!A:A,CODIGOS!B:B)," ") -> LA CARTUJA | H86: =IF(J86="SI",IFERROR(LOOKUP(E86,CODIGOS!A:A,CODIGOS!C:C)," "),IFERROR(LOOKUP(E86,CODIGOS!A:A,CODIGOS!D:D),"")) -> 7 | I86: =IFERROR(LOOKUP(C86,SOCIO!A:A,SOCIO!D:D)," ") -> SI | J86: =IFERROR(LOOKUP(D86,SOCIO!B:B,SOCIO!C:C)," ") -> SI
A87: =IF(B87<>0,A86+1," ") -> 86 | B87: 46049 | C87: =IFERROR(LOOKUP(D87,SOCIO!B:B,SOCIO!A:A),"") -> 2638 | D87: RUIZ RODRIGUEZ, PEPA | E87: 16 | F87: =IFERROR(LOOKUP(E87,CODIGOS!A:A,CODIGOS!B:B)," ") -> LA CARTUJA | H87: =IF(J87="SI",IFERROR(LOOKUP(E87,CODIGOS!A:A,CODIGOS!C:C)," "),IFERROR(LOOKUP(E87,CODIGOS!A:A,CODIGOS!D:D),"")) -> 7 | I87: =IFERROR(LOOKUP(C87,SOCIO!A:A,SOCIO!D:D)," ") -> NO | J87: =IFERROR(LOOKUP(D87,SOCIO!B:B,SOCIO!C:C)," ") -> SI
A88: =IF(B88<>0,A87+1," ") -> 87 | B88: 46049 | C88: =IFERROR(LOOKUP(D88,SOCIO!B:B,SOCIO!A:A),"") -> 2308 | D88: ZAFRA ALVAREZ, MARIA DEL CARMEN | E88: 16 | F88: =IFERROR(LOOKUP(E88,CODIGOS!A:A,CODIGOS!B:B)," ") -> LA CARTUJA | H88: =IF(J88="SI",IFERROR(LOOKUP(E88,CODIGOS!A:A,CODIGOS!C:C)," "),IFERROR(LOOKUP(E88,CODIGOS!A:A,CODIGOS!D:D),"")) -> 7 | I88: =IFERROR(LOOKUP(C88,SOCIO!A:A,SOCIO!D:D)," ") -> NO | J88: =IFERROR(LOOKUP(D88,SOCIO!B:B,SOCIO!C:C)," ") -> SI
A89: =IF(B89<>0,A88+1," ") -> 88 | B89: 46049 | C89: =IFERROR(LOOKUP(D89,SOCIO!B:B,SOCIO!A:A),"") -> 2854 | D89: CALABRUS CARAZO, JULIA MARIA | E89: 16 | F89: =IFERROR(LOOKUP(E89,CODIGOS!A:A,CODIGOS!B:B)," ") -> LA CARTUJA | H89: =IF(J89="SI",IFERROR(LOOKUP(E89,CODIGOS!A:A,CODIGOS!C:C)," "),IFERROR(LOOKUP(E89,CODIGOS!A:A,CODIGOS!D:D),"")) -> 7 | I89: =IFERROR(LOOKUP(C89,SOCIO!A:A,SOCIO!D:D)," ") -> SI | J89: =IFERROR(LOOKUP(D89,SOCIO!B:B,SOCIO!C:C)," ") -> SI
A90: =IF(B90<>0,A89+1," ") -> 89 | B90: 46049 | C90: =IFERROR(LOOKUP(D90,SOCIO!B:B,SOCIO!A:A),"") -> 1823 | D90: CAÑAVATE FERNANDEZ, MARIA CONCEPCION | E90: 14 | F90: =IFERROR(LOOKUP(E90,CODIGOS!A:A,CODIGOS!B:B)," ") -> BASÍLICA DE SAN JUAN DE DIOS | H90: =IF(J90="SI",IFERROR(LOOKUP(E90,CODIGOS!A:A,CODIGOS!C:C)," "),IFERROR(LOOKUP(E90,CODIGOS!A:A,CODIGOS!D:D),"")) -> 5 | I90: =IFERROR(LOOKUP(C90,SOCIO!A:A,SOCIO!D:D)," ") -> SI | J90: =IFERROR(LOOKUP(D90,SOCIO!B:B,SOCIO!C:C)," ") -> SI
A91: =IF(B91<>0,A90+1," ") -> 90 | B91: 46049 | C91: =IFERROR(LOOKUP(D91,SOCIO!B:B,SOCIO!A:A),"") -> 1945 | D91: CAÑAVATE FERNANDEZ, MARIA DEL CARMEN | E91: 14 | F91: =IFERROR(LOOKUP(E91,CODIGOS!A:A,CODIGOS!B:B)," ") -> BASÍLICA DE SAN JUAN DE DIOS | H91: =IF(J91="SI",IFERROR(LOOKUP(E91,CODIGOS!A:A,CODIGOS!C:C)," "),IFERROR(LOOKUP(E91,CODIGOS!A:A,CODIGOS!D:D),"")) -> 5 | I91: =IFERROR(LOOKUP(C91,SOCIO!A:A,SOCIO!D:D)," ") -> SI | J91: =IFERROR(LOOKUP(D91,SOCIO!B:B,SOCIO!C:C)," ") -> SI
A92: =IF(B92<>0,A91+1," ") -> 91 | B92: 46049 | C92: =IFERROR(LOOKUP(D92,SOCIO!B:B,SOCIO!A:A),"") -> 1928 | D92: CONSUEGRA NAVARRO, JOSE MARIA | E92: 14 | F92: =IFERROR(LOOKUP(E92,CODIGOS!A:A,CODIGOS!B:B)," ") -> BASÍLICA DE SAN JUAN DE DIOS | H92: =IF(J92="SI",IFERROR(LOOKUP(E92,CODIGOS!A:A,CODIGOS!C:C)," "),IFERROR(LOOKUP(E92,CODIGOS!A:A,CODIGOS!D:D),"")) -> 5 | I92: =IFERROR(LOOKUP(C92,SOCIO!A:A,SOCIO!D:D)," ") -> SI | J92: =IFERROR(LOOKUP(D92,SOCIO!B:B,SOCIO!C:C)," ") -> SI
A93: =IF(B93<>0,A92+1," ") -> 92 | B93: 46049 | C93: =IFERROR(LOOKUP(D93,SOCIO!B:B,SOCIO!A:A),"") -> 1823 | D93: CAÑAVATE FERNANDEZ, MARIA CONCEPCION | E93: 16 | F93: =IFERROR(LOOKUP(E93,CODIGOS!A:A,CODIGOS!B:B)," ") -> LA CARTUJA | H93: =IF(J93="SI",IFERROR(LOOKUP(E93,CODIGOS!A:A,CODIGOS!C:C)," "),IFERROR(LOOKUP(E93,CODIGOS!A:A,CODIGOS!D:D),"")) -> 7 | I93: =IFERROR(LOOKUP(C93,SOCIO!A:A,SOCIO!D:D)," ") -> SI | J93: =IFERROR(LOOKUP(D93,SOCIO!B:B,SOCIO!C:C)," ") -> SI
A94: =IF(B94<>0,A93+1," ") -> 93 | B94: 46049 | C94: =IFERROR(LOOKUP(D94,SOCIO!B:B,SOCIO!A:A),"") -> 1945 | D94: CAÑAVATE FERNANDEZ, MARIA DEL CARMEN | E94: 16 | F94: =IFERROR(LOOKUP(E94,CODIGOS!A:A,CODIGOS!B:B)," ") -> LA CARTUJA | H94: =IF(J94="SI",IFERROR(LOOKUP(E94,CODIGOS!A:A,CODIGOS!C:C)," "),IFERROR(LOOKUP(E94,CODIGOS!A:A,CODIGOS!D:D),"")) -> 7 | I94: =IFERROR(LOOKUP(C94,SOCIO!A:A,SOCIO!D:D)," ") -> SI | J94: =IFERROR(LOOKUP(D94,SOCIO!B:B,SOCIO!C:C)," ") -> SI
A95: =IF(B95<>0,A94+1," ") -> 94 | B95: 46049 | C95: =IFERROR(LOOKUP(D95,SOCIO!B:B,SOCIO!A:A),"") -> 1928 | D95: CONSUEGRA NAVARRO, JOSE MARIA | E95: 16 | F95: =IFERROR(LOOKUP(E95,CODIGOS!A:A,CODIGOS!B:B)," ") -> LA CARTUJA | H95: =IF(J95="SI",IFERROR(LOOKUP(E95,CODIGOS!A:A,CODIGOS!C:C)," "),IFERROR(LOOKUP(E95,CODIGOS!A:A,CODIGOS!D:D),"")) -> 7 | I95: =IFERROR(LOOKUP(C95,SOCIO!A:A,SOCIO!D:D)," ") -> SI | J95: =IFERROR(LOOKUP(D95,SOCIO!B:B,SOCIO!C:C)," ") -> SI
A96: =IF(B96<>0,A95+1," ") -> 95 | B96: 46055 | C96: =IFERROR(LOOKUP(D96,SOCIO!B:B,SOCIO!A:A),"") -> 2874 | D96: FERNANDEZ FERNANDEZ, FRANCISCA | E96: 17 | F96: =IFERROR(LOOKUP(E96,CODIGOS!A:A,CODIGOS!B:B)," ") -> VISITA CASA DE LOS PISAS | H96: 5 | J96: =IFERROR(LOOKUP(D96,SOCIO!B:B,SOCIO!C:C)," ") -> SI
A97: =IF(B97<>0,A96+1," ") -> 96 | B97: 46055 | C97: =IFERROR(LOOKUP(D97,SOCIO!B:B,SOCIO!A:A),"") -> 2874 | D97: FERNANDEZ FERNANDEZ, FRANCISCA | E97: 16 | F97: =IFERROR(LOOKUP(E97,CODIGOS!A:A,CODIGOS!B:B)," ") -> LA CARTUJA | H97: =IF(J97="SI",IFERROR(LOOKUP(E97,CODIGOS!A:A,CODIGOS!C:C)," "),IFERROR(LOOKUP(E97,CODIGOS!A:A,CODIGOS!D:D),"")) -> 7 | J97: =IFERROR(LOOKUP(D97,SOCIO!B:B,SOCIO!C:C)," ") -> SI
A98: =IF(B98<>0,A97+1," ") -> 97 | B98: 46055 | C98: =IFERROR(LOOKUP(D98,SOCIO!B:B,SOCIO!A:A),"") -> 3049 | D98: FERNANDEZ FERNANDEZ , MARIA GLORIA | E98: 16 | F98: =IFERROR(LOOKUP(E98,CODIGOS!A:A,CODIGOS!B:B)," ") -> LA CARTUJA | H98: =IF(J98="SI",IFERROR(LOOKUP(E98,CODIGOS!A:A,CODIGOS!C:C)," "),IFERROR(LOOKUP(E98,CODIGOS!A:A,CODIGOS!D:D),"")) -> 7 | J98: =IFERROR(LOOKUP(D98,SOCIO!B:B,SOCIO!C:C)," ") -> SI
A99: =IF(B99<>0,A98+1," ") -> 98 | B99: 46055 | C99: =IFERROR(LOOKUP(D99,SOCIO!B:B,SOCIO!A:A),"") -> 2642 | D99: MOYANO REDONDO , JULIO | E99: 16 | F99: =IFERROR(LOOKUP(E99,CODIGOS!A:A,CODIGOS!B:B)," ") -> LA CARTUJA | H99: =IF(J99="SI",IFERROR(LOOKUP(E99,CODIGOS!A:A,CODIGOS!C:C)," "),IFERROR(LOOKUP(E99,CODIGOS!A:A,CODIGOS!D:D),"")) -> 7 | J99: =IFERROR(LOOKUP(D99,SOCIO!B:B,SOCIO!C:C)," ") -> SI
A100: =IF(B100<>0,A99+1," ") -> 99 | B100: 46056 | C100: =IFERROR(LOOKUP(D100,SOCIO!B:B,SOCIO!A:A),"") -> 3000 | D100: LOPEZ PUERTAS , ANTONIO | E100: 16 | F100: =IFERROR(LOOKUP(E100,CODIGOS!A:A,CODIGOS!B:B)," ") -> LA CARTUJA | H100: =IF(J100="SI",IFERROR(LOOKUP(E100,CODIGOS!A:A,CODIGOS!C:C)," "),IFERROR(LOOKUP(E100,CODIGOS!A:A,CODIGOS!D:D),"")) -> 7 | J100: =IFERROR(LOOKUP(D100,SOCIO!B:B,SOCIO!C:C)," ") -> SI
A101: =IF(B101<>0,A100+1," ") -> 100 | B101: 46056 | C101: A/3000 | D101: JAIMEZ ENCARNI | E101: 16 | F101: =IFERROR(LOOKUP(E101,CODIGOS!A:A,CODIGOS!B:B)," ") -> LA CARTUJA | H101: =IF(J8100="SI",IFERROR(LOOKUP(E101,CODIGOS!A:A,CODIGOS!C:C)," "),IFERROR(LOOKUP(E101,CODIGOS!A:A,CODIGOS!D:D),"")) -> 8 | J101: =IFERROR(LOOKUP(D101,SOCIO!B:B,SOCIO!C:C)," ") -> SI
A102: =IF(B102<>0,A101+1," ") -> 101 | B102: 46056 | C102: =IFERROR(LOOKUP(D102,SOCIO!B:B,SOCIO!A:A),"") -> 1930 | D102: CORRALES CARRETERO, MANUEL | E102: 4 | F102: =IFERROR(LOOKUP(E102,CODIGOS!A:A,CODIGOS!B:B)," ") -> DEVOLUCION | G102: M CASA PISA | H102: -5 | J102: =IFERROR(LOOKUP(D102,SOCIO!B:B,SOCIO!C:C)," ") -> SI
...

Sheet Hoja1

Sheet SOCIOS
A1: Nº Socio | B1: NOMBRE | C1: DNI | D1: DOMICILIO | E1: COD. POSTAL | F1: MUNICIPIO | G1: TELEFONO | H1: CORREO
A2: 269 | B2: JUAN FRANCISCO ACEÑA CABALLERO | C2: 1121212A | D2: PETRA,32 | E2: 18001 | F2: GRANADA | G2: 658555555 | H2: pepe@dsds
A3: 410 | B3: LUCIA LOPEZ BIEZMA | C3: 1121212A | D3: PETRA,33 | E3: 18002 | F3: GRANADA | G3: 658555556 | H3: pepe@dsds
A4: 575 | B4: TERESA BAUTISTA MENDEZ | C4: 1121212A | D4: PETRA,34 | E4: 18003 | F4: GRANADA | G4: 658555557 | H4: pepe@dsds
A5: 738 | B5: Mª TERESA ROZUA LARIOS | C5: 1121212A | D5: PETRA,35 | E5: 18004 | F5: GRANADA | G5: 658555558 | H5: pepe@dsds
A6: 810 | B6: Dionisio Gonzalez Gonzalez | C6: 1121212A | D6: PETRA,36 | E6: 18005 | F6: GRANADA | G6: 658555559 | H6: pepe@dsds
A7: 849 | B7: Purificación Rodríguez Franco | C7: 1121212A | D7: PETRA,37 | E7: 18006 | F7: GRANADA | G7: 658555560 | H7: pepe@dsds
A8: 1030 | B8: ANTONIO ALCALDE CASTILLA | C8: 1121212A | D8: PETRA,38 | E8: 18007 | F8: GRANADA | G8: 658555561 | H8: pepe@dsds
A9: 1042 | B9: LEONARDO SEGURA HERRERA | C9: 1121212A | D9: PETRA,39 | E9: 18008 | F9: GRANADA | G9: 658555562 | H9: pepe@dsds
A10: 1045 | B10: SANCHEZ ROMERO MARÍA | C10: 1121212A | D10: PETRA,40 | E10: 18009 | F10: GRANADA | G10: 658555563 | H10: pepe@dsds
A11: 1141 | B11: PILAR ESTRELLA MANCILLA GUARDIA | C11: 1121212A | D11: PETRA,41 | E11: 18010 | F11: GRANADA | G11: 658555564 | H11: pepe@dsds
A12: 1178 | B12: Rufo del Castillo Gordo | C12: 1121212A | D12: PETRA,42 | E12: 18011 | F12: GRANADA | G12: 658555565 | H12: pepe@dsds
A13: 1251 | B13: Maria Hortencia Martinez Raya | C13: 1121212A | D13: PETRA,43 | E13: 18012 | F13: GRANADA | G13: 658555566 | H13: pepe@dsds
... A20: 1623 | B20: Mercedes Rios Collantes | C20: 1121212A | D20: PETRA,50 | E20: 18019 | F20: GRANADA | G20: 658555573 | H20: pepe@dsds
A21: 1674 | B21: Antonio Fernández Cabello
A22: 1680 | B22: LOLI CONTRERAS GONZALEZ
A23: 1744 | B23: Mª DEL PILAR DE MAQUA MONTEYS
A24: 1745 | B24: LOLA CANTARERO CABALLERO
A25: 1803 | B25: MARI CARMEN JIMENEZ BARRIONUEVO
A26: 1815 | B26: Mº Concepcion Fdez Montoya
A27: 1823 | B27: INMA CAÑAVATE
A28: 1836 | B28: MARTIN CHIROSA TERESA
A29: 1853 | B29: ENRIQUE ARBOL JIMENEZ
A30: 1856 | B30: DOLORES ROMAN ENRIQUEZ
A31: 1861 | B31: Maria Isabel Martin Aguilar
A32: 1888 | B32: Maria Navarro de la Casa
... A320: 5000 | B320: ACOMPAÑANTE

Sheet SOCIO
A1: NUMERO | B1: SOCIO | C1: ACTIVO | D1: matricula
A2: 2411 | B2: ACEBAL MIÑANO, MARIA DEL MILAGRO | C2: SI | D2: SI
A3: 2303 | B3: ACEBES ORIHUELA, FRANCISCA | C3: SI | D3: SI
A4: 269 | B4: ACEÑA CABALLERO, JUAN FRANCISCO | C4: SI | D4: NO
A5: 3045 | B5: ACOSTA ROBLES, PABLO | C5: SI | D5: SI
A6: 2940 | B6: AGUILAR RAMIREZ, JOSE | C6: SI | D6: SI
A7: 2773 | B7: AGUIRRE GALLEGO, JOSE LUIS | C7: SI | D7: NO
A8: 2377 | B8: ALCALA VILCHEZ, MANUEL | C8: SI | D8: SI
A9: 1030 | B9: ALCALDE CASTILLA, ANTONIO | C9: SI | D9: SI
A10: 2369 | B10: ALGAR REYES , LEONOR | C10: SI | D10: SI
A11: 2505 | B11: ALONSO SAEZ, INMACULADA | C11: SI | D11: SI
A12: 2419 | B12: ALVAREZ DE CIENFUEGOS LOPEZ, CARMEN | C12: SI | D12: SI
A13: 3047 | B13: ALVAREZ MARTINEZ,, YOLANDA | C13: SI | D13: SI
... A196: 3046 | B196: GONZALEZ RODRIGUEZ, MARIA DOLORES | C196: SI | D196: SI
A197: 3112 | B197: GRANERO EXPÓSITO, ESPERANZA | C197: SI
A198: 2817 | B198: GUERRERO BARQUERO, JOSE ANTONIO | C198: SI | D198: SI
A199: 3130 | B199: GUERRERO JIMÉNEZ, AMPARO | C199: SI | D199: SI
A200: 3129 | B200: GUERRERO SOLANO, NIEVES | C200: SI | D200: SI
A201: 2902 | B201: GUILLEN GONZALEZ -NOVO , EDUARDO | C201: SI | D201: SI
A202: 2850 | B202: GUTIERREZ MELENDEZ, VICENTA | C202: SI | D202: SI
A203: 2524 | B203: GUZMAN LIRIO, MARIA ANGUSTIAS | C203: SI | D203: SI
A204: 2885 | B204: HARO ARRABAL, AFRICA | C204: SI | D204: SI
A205: 1920 | B205: HERAS JIMENEZ, JOSE FRANCISCO | C205: SI | D205: SI
A206: 2923 | B206: HERNANDEZ OGAYAR, PAULA | C206: SI | D206: SI
A207: 3139 | B207: HERNANDEZ PRIETO, JUAN | C207: SI | D207: SI
A208: 2584 | B208: HERNANDEZ VALLECILLO, MARIA TERESA | C208: SI | D208: SI
A209: 2614 | B209: HERVIAS GARRIDO, Mª REMEDIOS | C209: SI | D209: SI
... A319: 2881 | B319: MONTERO ORTIZ, MARIA TERESA | C319: SI | D319: SI
A320: 2978 | B320: MONTES GOMEZ, MARIA DEL CAEMEN | C320: SI
A321: 3072 | B321: MONTORE MONTORE, MARIA DEL PILAR | C321: SI | D321: NO
A322: 3002 | B322: MONTOYA RAMÍREZ, ROSALÍA | C322: SI | D322: SI
A323: 2991 | B323: MORA DE SAAVEDRA, ROSARIO | C323: SI | D323: SI
A324: 2983 | B324: MORALES BRAOJOS, MARIA DEL MAR | C324: SI | D324: SI
A325: 3122 | B325: MORALES DUARTE, MARIA DOLORES | C325: SI | D325: SI
A326: 2877 | B326: MORALES GARCÍA, Mª TRINIDAD | C326: SI | D326: SI
A327: 2532 | B327: MORALES GONZALEZ, VALERIANO | C327: SI | D327: SI
A328: 3064 | B328: MORALES PASADAS, CRISTOBAL JOSE | C328: SI | D328: SI
A329: 3103 | B329: MORALLON FUENTES, M. DEL CARMEN | C329: SI | D329: NO
A330: 3071 | B330: MORENO MARTINEZ, ROSA MARÍA | C330: SI | D330: SI
A331: 2516 | B331: MORENO MORENO, JOSE LUIS | C331: SI | D331: SI
A332: 2734 | B332: MORENO SANCHEZ , JUAN | C332: SI | D332: SI
... A336: 2763 | B336: MORÓN ALCALDE, Mª LEONOR | C336: SI | D336: SI
A337: 3108 | B337: MORÓN GALLARDO, TERESA | C337: SI
A338: 2625 | B338: MOYA AYAN , MANUEL | C338: SI | D338: SI
A339: 2642 | B339: MOYANO REDONDO , JULIO | C339: SI | D339: SI
A340: 3107 | B340: MUÑOZ DE DIOS, MARIA VICTORIA | C340: SI | D340: SI
A341: 2896 | B341: MUÑOZ EXTRAVIZ, MARIA FILOMENA | C341: SI | D341: SI
A342: 3123 | B342: MUÑOZ FUENTES, MARIA FRANCISCA | C342: SI | D342: SI
A343: 3004 | B343: MUÑOZ GARZÓN, Mª CARMEN | C343: SI | D343: SI
A344: 2403 | B344: MUÑOZ ROPERO , JENARO | C344: SI | D344: SI
A345: 2900 | B345: MURILLO, HELMER | C345: SI | D345: SI
A346: 2872 | B346: MUROS JIMENEZ, ENCARNACION | C346: SI | D346: SI
A347: 1888 | B347: NAVARRO DE LA CASA, MARIA | C347: SI | D347: NO
A348: 2662 | B348: NAVARRO MEDINA, PEDRO | C348: SI | D348: SI
A349: 2987 | B349: NAVARRO NAVARRO, ANA MARIA | C349: SI | D349: SI
... A543: 2671 | B543: ZURITA JIMENEZ, MANUEL | C543: SI | D543: SI

Sheet RECIBO
D1: RECIBO Nº
D2: 177
D4: º
B5: ALUMA
B6: ASOCIACIÓN DE ALUMNOS DEL AULA
B7: PERMANENTE DE FORMACIÓN ABIERTA
B8: UNIVERSIDAD DE GRANADA
B9: N.I.F. G18429068
B10: Avd. Madrid, 3 Espacio V Centenario
B11: 18070 - GRANADA
B13: =CONCATENATE("RECIBO Nº ",D2) -> RECIBO Nº 177
B15: Hemos recibido de
B16: =IFERROR(LOOKUP(D2,'DIARIO 2026'!A:A,'DIARIO 2026'!D:D)," ") -> MOYANO REDONDO , JULIO
B17: =CONCATENATE("la cantidad de ",LOOKUP(D2,'DIARIO 2026'!A:A,'DIARIO 2026'!H:H)," Euros") -> la cantidad de 20 Euros
B18: en concepto de
B19: =LOOKUP(D2,'DIARIO 2026'!A:A,'DIARIO 2026'!F:F) -> VISITA A FONELAS
B20: =IFERROR(LOOKUP(D2,'DIARIO 2026'!A:A,'DIARIO 2026'!B:B)," ") -> 46070
I235: =+RECIBO!D2232 -> 0

Sheet CODIGOS
A1: COD | B1: CONCEPTO | C1: IMPORTE | D1: NO SOCIO
A2: 1 | B2: CUOTA SOCIO | C2: 30
A3: 2 | B3: CUOTA NUEVO SOCIO | C3: 30
A4: 3
A5: 4 | B5: DEVOLUCION
A6: 5
A7: 6
A8: 7
A9: 8
A10: 9
A11: 10 | B11: ÓRGIVA | C11: 22 | D11: 27
A12: 11 | B12: OLLA SAN ANTÓN | C12: 25 | D12: 30
A13: 12 | B13: EXPOSICIÓN CATEDRAL | C13: 3 | D13: 3
A14: 13 | B14: ENSAYO ORQUESTA | C14: 0 | D14: 0
A15: 14 | B15: BASÍLICA DE SAN JUAN DE DIOS | C15: 5 | D15: 6
A16: 15 | B16: MUSEO SAN JUAN DE DIOS CP | C16: 5 | D16: 6
A17: 16 | B17: LA CARTUJA | C17: 7 | D17: 8
A18: 17 | B18: VISITA CASA DE LOS PISAS | C18: 5 | D18: 5
A19: 18 | B19: COMIDA DE PATRONA | C19: 55
A20: 19 | B20: VISITA MOTRIL | C20: 15
A21: 20 | B21: VISITA A FONELAS | C21: 20 | D21: 25
A22: 21
A23: 22
A24: 23
A25: 24
A26: 25
A27: 26
A28: 27
A29: 28
A30: 29
A31: 30
A32: 31
A33: 32
... A57: 99

Sheet FACTURAS
A1: DATOS FACTURA | J1: PAGO | N1: ACTIVIDAD
A2: ORDEN | B2: FECHA | C2: NÚMERO | D2: ACREEDOR | E2: CONCEPTO | F2: BASE | G2: IVA | H2: IRPF | I2: TOTAL | J2: P | K2: FECHA | L2: IMPORTE | M2: OBSER. | N2: COD. | O2: DENOMINACIÓN
O3: =IFERROR(LOOKUP(N:N,CODIGOS!A:A,CODIGOS!B:B),"")
O4: =IFERROR(LOOKUP(N:N,CODIGOS!A:A,CODIGOS!B:B),"")
O5: =IFERROR(LOOKUP(N:N,CODIGOS!A:A,CODIGOS!B:B),"")
O6: =IFERROR(LOOKUP(N:N,CODIGOS!A:A,CODIGOS!B:B),"")
O7: =IFERROR(LOOKUP(N:N,CODIGOS!A:A,CODIGOS!B:B),"")
O8: =IFERROR(LOOKUP(N:N,CODIGOS!A:A,CODIGOS!B:B),"")
O9: =IFERROR(LOOKUP(N:N,CODIGOS!A:A,CODIGOS!B:B),"")
O10: =IFERROR(LOOKUP(N:N,CODIGOS!A:A,CODIGOS!B:B),"")
O11: =IFERROR(LOOKUP(N:N,CODIGOS!A:A,CODIGOS!B:B),"")
O12: =IFERROR(LOOKUP(N:N,CODIGOS!A:A,CODIGOS!B:B),"")
O13: =IFERROR(LOOKUP(N:N,CODIGOS!A:A,CODIGOS!B:B),"")
O14: =IFERROR(LOOKUP(N:N,CODIGOS!A:A,CODIGOS!B:B),"")
... O238: =IFERROR(LOOKUP(N:N,CODIGOS!A:A,CODIGOS!B:B),"")

Sheet ACREED
